<?xml version="1.0" encoding="UTF-8" standalone="yes"?>
<dgm:dataModel xmlns:dgm="http://schemas.openxmlformats.org/drawingml/2006/diagram" xmlns:a="http://schemas.openxmlformats.org/drawingml/2006/main"><dgm:ptLst><dgm:pt modelId="{0F97D2EB-F034-4B23-9D36-9847EE47DA80}" type="doc"><dgm:prSet loTypeId="urn:microsoft.com/office/officeart/2005/8/layout/equation2" loCatId="relationship" qsTypeId="urn:microsoft.com/office/officeart/2005/8/quickstyle/simple1" qsCatId="simple" csTypeId="urn:microsoft.com/office/officeart/2005/8/colors/accent1_2" csCatId="accent1" phldr="1"/><dgm:spPr/></dgm:pt><dgm:pt modelId="{D3C75C3E-D432-4DDE-AF4F-DDB38E4C3D8C}"><dgm:prSet phldrT="[Text]"/><dgm:spPr><a:solidFill><a:srgbClr val="CC9900"/></a:solidFill></dgm:spPr><dgm:t><a:bodyPr/><a:lstStyle/><a:p><a:r><a:rPr lang="sv-SE"/><a:t>Karin Gummesdotter</a:t></a:r></a:p><a:p><a:r><a:rPr lang="sv-SE"/><a:t>1730-1808</a:t></a:r></a:p></dgm:t></dgm:pt><dgm:pt modelId="{D2B6F9E5-B46B-4E46-A15B-CB84AAB658DA}" type="parTrans" cxnId="{E742C53B-C91F-4EE5-8136-8666631CC271}"><dgm:prSet/><dgm:spPr/><dgm:t><a:bodyPr/><a:lstStyle/><a:p><a:endParaRPr lang="sv-SE"/></a:p></dgm:t></dgm:pt><dgm:pt modelId="{B70B6A80-24F5-496E-881D-A8B286103C10}" type="sibTrans" cxnId="{E742C53B-C91F-4EE5-8136-8666631CC271}"><dgm:prSet/><dgm:spPr/><dgm:t><a:bodyPr/><a:lstStyle/><a:p><a:endParaRPr lang="sv-SE"/></a:p></dgm:t></dgm:pt><dgm:pt modelId="{949B21F3-D5F7-4A20-9ECC-175BCB73C3B3}"><dgm:prSet phldrT="[Text]"/><dgm:spPr><a:solidFill><a:srgbClr val="CC9900"/></a:solidFill></dgm:spPr><dgm:t><a:bodyPr/><a:lstStyle/><a:p><a:r><a:rPr lang="sv-SE"/><a:t>Måns Månsson</a:t></a:r></a:p><a:p><a:r><a:rPr lang="sv-SE"/><a:t>1721-1784</a:t></a:r></a:p></dgm:t></dgm:pt><dgm:pt modelId="{A0F2933B-EDCD-40D7-95F4-42AC9F3A41C9}" type="parTrans" cxnId="{0377CB0B-FF33-40BD-A540-2B902EDECCFA}"><dgm:prSet/><dgm:spPr/><dgm:t><a:bodyPr/><a:lstStyle/><a:p><a:endParaRPr lang="sv-SE"/></a:p></dgm:t></dgm:pt><dgm:pt modelId="{9F1CDB7E-0B98-440D-9803-A48C009FA4B6}" type="sibTrans" cxnId="{0377CB0B-FF33-40BD-A540-2B902EDECCFA}"><dgm:prSet/><dgm:spPr/><dgm:t><a:bodyPr/><a:lstStyle/><a:p><a:endParaRPr lang="sv-SE"/></a:p></dgm:t></dgm:pt><dgm:pt modelId="{C961B963-43BC-40E0-9C3B-5D1F847D82C8}"><dgm:prSet phldrT="[Text]"/><dgm:spPr><a:solidFill><a:schemeClr val="accent4"/></a:solidFill></dgm:spPr><dgm:t><a:bodyPr/><a:lstStyle/><a:p><a:r><a:rPr lang="sv-SE"><a:solidFill><a:sysClr val="windowText" lastClr="000000"/></a:solidFill></a:rPr><a:t>Peter Månsson Dansare</a:t></a:r></a:p><a:p><a:r><a:rPr lang="sv-SE"><a:solidFill><a:sysClr val="windowText" lastClr="000000"/></a:solidFill></a:rPr><a:t>1759-1840</a:t></a:r></a:p><a:p><a:endParaRPr lang="sv-SE"><a:solidFill><a:sysClr val="windowText" lastClr="000000"/></a:solidFill></a:endParaRPr></a:p></dgm:t></dgm:pt><dgm:pt modelId="{EF02D3F4-EE6B-4538-AB22-26AF2ECACE61}" type="parTrans" cxnId="{18AC92E2-EDF1-470E-AA20-9035437B5421}"><dgm:prSet/><dgm:spPr/><dgm:t><a:bodyPr/><a:lstStyle/><a:p><a:endParaRPr lang="sv-SE"/></a:p></dgm:t></dgm:pt><dgm:pt modelId="{6DA2D973-483F-4339-BF27-3A8A089CA8AC}" type="sibTrans" cxnId="{18AC92E2-EDF1-470E-AA20-9035437B5421}"><dgm:prSet/><dgm:spPr/><dgm:t><a:bodyPr/><a:lstStyle/><a:p><a:endParaRPr lang="sv-SE"/></a:p></dgm:t></dgm:pt><dgm:pt modelId="{3DF62598-B0EC-46B4-9B24-40796A2F6228}" type="pres"><dgm:prSet presAssocID="{0F97D2EB-F034-4B23-9D36-9847EE47DA80}" presName="Name0" presStyleCnt="0"><dgm:presLayoutVars><dgm:dir/><dgm:resizeHandles val="exact"/></dgm:presLayoutVars></dgm:prSet><dgm:spPr/></dgm:pt><dgm:pt modelId="{7BA8FF75-BD99-46F3-B828-9324DBE92316}" type="pres"><dgm:prSet presAssocID="{0F97D2EB-F034-4B23-9D36-9847EE47DA80}" presName="vNodes" presStyleCnt="0"/><dgm:spPr/></dgm:pt><dgm:pt modelId="{60E506FA-1703-4BCC-84F7-E72E9947593E}" type="pres"><dgm:prSet presAssocID="{D3C75C3E-D432-4DDE-AF4F-DDB38E4C3D8C}" presName="node" presStyleLbl="node1" presStyleIdx="0" presStyleCnt="3"><dgm:presLayoutVars><dgm:bulletEnabled val="1"/></dgm:presLayoutVars></dgm:prSet><dgm:spPr/></dgm:pt><dgm:pt modelId="{DE149E94-00EB-43C0-A3D8-1485CFFDBC87}" type="pres"><dgm:prSet presAssocID="{B70B6A80-24F5-496E-881D-A8B286103C10}" presName="spacerT" presStyleCnt="0"/><dgm:spPr/></dgm:pt><dgm:pt modelId="{E983D192-956B-4737-82D2-76A523CD676A}" type="pres"><dgm:prSet presAssocID="{B70B6A80-24F5-496E-881D-A8B286103C10}" presName="sibTrans" presStyleLbl="sibTrans2D1" presStyleIdx="0" presStyleCnt="2"/><dgm:spPr/></dgm:pt><dgm:pt modelId="{7438FDD8-21FC-4F74-8EA8-EC5C4BBC1501}" type="pres"><dgm:prSet presAssocID="{B70B6A80-24F5-496E-881D-A8B286103C10}" presName="spacerB" presStyleCnt="0"/><dgm:spPr/></dgm:pt><dgm:pt modelId="{6ED9D99A-A5E7-43D8-83CD-B7CF65EF9FCF}" type="pres"><dgm:prSet presAssocID="{949B21F3-D5F7-4A20-9ECC-175BCB73C3B3}" presName="node" presStyleLbl="node1" presStyleIdx="1" presStyleCnt="3"><dgm:presLayoutVars><dgm:bulletEnabled val="1"/></dgm:presLayoutVars></dgm:prSet><dgm:spPr/></dgm:pt><dgm:pt modelId="{748E2794-F7D1-4228-AC89-64EF58385E4B}" type="pres"><dgm:prSet presAssocID="{0F97D2EB-F034-4B23-9D36-9847EE47DA80}" presName="sibTransLast" presStyleLbl="sibTrans2D1" presStyleIdx="1" presStyleCnt="2"/><dgm:spPr/></dgm:pt><dgm:pt modelId="{BA43A3B0-0BA7-448C-B7E4-523F2A344BCB}" type="pres"><dgm:prSet presAssocID="{0F97D2EB-F034-4B23-9D36-9847EE47DA80}" presName="connectorText" presStyleLbl="sibTrans2D1" presStyleIdx="1" presStyleCnt="2"/><dgm:spPr/></dgm:pt><dgm:pt modelId="{34C463BA-2069-471E-9BAD-D8B570661A6E}" type="pres"><dgm:prSet presAssocID="{0F97D2EB-F034-4B23-9D36-9847EE47DA80}" presName="lastNode" presStyleLbl="node1" presStyleIdx="2" presStyleCnt="3"><dgm:presLayoutVars><dgm:bulletEnabled val="1"/></dgm:presLayoutVars></dgm:prSet><dgm:spPr/></dgm:pt></dgm:ptLst><dgm:cxnLst><dgm:cxn modelId="{0377CB0B-FF33-40BD-A540-2B902EDECCFA}" srcId="{0F97D2EB-F034-4B23-9D36-9847EE47DA80}" destId="{949B21F3-D5F7-4A20-9ECC-175BCB73C3B3}" srcOrd="1" destOrd="0" parTransId="{A0F2933B-EDCD-40D7-95F4-42AC9F3A41C9}" sibTransId="{9F1CDB7E-0B98-440D-9803-A48C009FA4B6}"/><dgm:cxn modelId="{0D284E14-B6CC-4913-B08F-A1E1968181B6}" type="presOf" srcId="{0F97D2EB-F034-4B23-9D36-9847EE47DA80}" destId="{3DF62598-B0EC-46B4-9B24-40796A2F6228}" srcOrd="0" destOrd="0" presId="urn:microsoft.com/office/officeart/2005/8/layout/equation2"/><dgm:cxn modelId="{75B86E16-C02E-4613-9687-4EF7ABA27704}" type="presOf" srcId="{9F1CDB7E-0B98-440D-9803-A48C009FA4B6}" destId="{748E2794-F7D1-4228-AC89-64EF58385E4B}" srcOrd="0" destOrd="0" presId="urn:microsoft.com/office/officeart/2005/8/layout/equation2"/><dgm:cxn modelId="{1BC5201B-9D0A-4933-8576-693A8B44343F}" type="presOf" srcId="{949B21F3-D5F7-4A20-9ECC-175BCB73C3B3}" destId="{6ED9D99A-A5E7-43D8-83CD-B7CF65EF9FCF}" srcOrd="0" destOrd="0" presId="urn:microsoft.com/office/officeart/2005/8/layout/equation2"/><dgm:cxn modelId="{E742C53B-C91F-4EE5-8136-8666631CC271}" srcId="{0F97D2EB-F034-4B23-9D36-9847EE47DA80}" destId="{D3C75C3E-D432-4DDE-AF4F-DDB38E4C3D8C}" srcOrd="0" destOrd="0" parTransId="{D2B6F9E5-B46B-4E46-A15B-CB84AAB658DA}" sibTransId="{B70B6A80-24F5-496E-881D-A8B286103C10}"/><dgm:cxn modelId="{C888B361-B8E7-4F9A-8E10-5918F222729F}" type="presOf" srcId="{B70B6A80-24F5-496E-881D-A8B286103C10}" destId="{E983D192-956B-4737-82D2-76A523CD676A}" srcOrd="0" destOrd="0" presId="urn:microsoft.com/office/officeart/2005/8/layout/equation2"/><dgm:cxn modelId="{0389906C-8E7A-4B01-9021-C56772F79C73}" type="presOf" srcId="{D3C75C3E-D432-4DDE-AF4F-DDB38E4C3D8C}" destId="{60E506FA-1703-4BCC-84F7-E72E9947593E}" srcOrd="0" destOrd="0" presId="urn:microsoft.com/office/officeart/2005/8/layout/equation2"/><dgm:cxn modelId="{3DD2509E-6577-4912-931B-B3B433E39B6A}" type="presOf" srcId="{C961B963-43BC-40E0-9C3B-5D1F847D82C8}" destId="{34C463BA-2069-471E-9BAD-D8B570661A6E}" srcOrd="0" destOrd="0" presId="urn:microsoft.com/office/officeart/2005/8/layout/equation2"/><dgm:cxn modelId="{18AC92E2-EDF1-470E-AA20-9035437B5421}" srcId="{0F97D2EB-F034-4B23-9D36-9847EE47DA80}" destId="{C961B963-43BC-40E0-9C3B-5D1F847D82C8}" srcOrd="2" destOrd="0" parTransId="{EF02D3F4-EE6B-4538-AB22-26AF2ECACE61}" sibTransId="{6DA2D973-483F-4339-BF27-3A8A089CA8AC}"/><dgm:cxn modelId="{2B6C7BF0-997C-420A-840F-EC31D07E6CD7}" type="presOf" srcId="{9F1CDB7E-0B98-440D-9803-A48C009FA4B6}" destId="{BA43A3B0-0BA7-448C-B7E4-523F2A344BCB}" srcOrd="1" destOrd="0" presId="urn:microsoft.com/office/officeart/2005/8/layout/equation2"/><dgm:cxn modelId="{AF20D562-6767-49A6-9129-45E11C4CAFB0}" type="presParOf" srcId="{3DF62598-B0EC-46B4-9B24-40796A2F6228}" destId="{7BA8FF75-BD99-46F3-B828-9324DBE92316}" srcOrd="0" destOrd="0" presId="urn:microsoft.com/office/officeart/2005/8/layout/equation2"/><dgm:cxn modelId="{73400B73-F63D-43D2-B457-B839191387AA}" type="presParOf" srcId="{7BA8FF75-BD99-46F3-B828-9324DBE92316}" destId="{60E506FA-1703-4BCC-84F7-E72E9947593E}" srcOrd="0" destOrd="0" presId="urn:microsoft.com/office/officeart/2005/8/layout/equation2"/><dgm:cxn modelId="{1C1C3079-6E25-4A35-AC70-E7DCEC2BDB35}" type="presParOf" srcId="{7BA8FF75-BD99-46F3-B828-9324DBE92316}" destId="{DE149E94-00EB-43C0-A3D8-1485CFFDBC87}" srcOrd="1" destOrd="0" presId="urn:microsoft.com/office/officeart/2005/8/layout/equation2"/><dgm:cxn modelId="{2792D2AC-1494-4AA5-A5A9-62385B2EC5BC}" type="presParOf" srcId="{7BA8FF75-BD99-46F3-B828-9324DBE92316}" destId="{E983D192-956B-4737-82D2-76A523CD676A}" srcOrd="2" destOrd="0" presId="urn:microsoft.com/office/officeart/2005/8/layout/equation2"/><dgm:cxn modelId="{A34EA005-CF7E-47C8-AD11-08AEF60040AC}" type="presParOf" srcId="{7BA8FF75-BD99-46F3-B828-9324DBE92316}" destId="{7438FDD8-21FC-4F74-8EA8-EC5C4BBC1501}" srcOrd="3" destOrd="0" presId="urn:microsoft.com/office/officeart/2005/8/layout/equation2"/><dgm:cxn modelId="{08C69FC7-1F07-4F46-8001-8DE8EC1E4EEF}" type="presParOf" srcId="{7BA8FF75-BD99-46F3-B828-9324DBE92316}" destId="{6ED9D99A-A5E7-43D8-83CD-B7CF65EF9FCF}" srcOrd="4" destOrd="0" presId="urn:microsoft.com/office/officeart/2005/8/layout/equation2"/><dgm:cxn modelId="{CD49ED18-28AC-477F-B90A-24E80D84528E}" type="presParOf" srcId="{3DF62598-B0EC-46B4-9B24-40796A2F6228}" destId="{748E2794-F7D1-4228-AC89-64EF58385E4B}" srcOrd="1" destOrd="0" presId="urn:microsoft.com/office/officeart/2005/8/layout/equation2"/><dgm:cxn modelId="{EF56D6A5-4622-4261-B700-CACF56085548}" type="presParOf" srcId="{748E2794-F7D1-4228-AC89-64EF58385E4B}" destId="{BA43A3B0-0BA7-448C-B7E4-523F2A344BCB}" srcOrd="0" destOrd="0" presId="urn:microsoft.com/office/officeart/2005/8/layout/equation2"/><dgm:cxn modelId="{32F26D3C-A9D0-4328-BD07-4915817E2720}" type="presParOf" srcId="{3DF62598-B0EC-46B4-9B24-40796A2F6228}" destId="{34C463BA-2069-471E-9BAD-D8B570661A6E}" srcOrd="2" destOrd="0" presId="urn:microsoft.com/office/officeart/2005/8/layout/equation2"/></dgm:cxnLst><dgm:bg/><dgm:whole/><dgm:extLst><a:ext uri="http://schemas.microsoft.com/office/drawing/2008/diagram"><dsp:dataModelExt xmlns:dsp="http://schemas.microsoft.com/office/drawing/2008/diagram" relId="rId283" minVer="http://schemas.openxmlformats.org/drawingml/2006/diagram"/></a:ext></dgm:extLst></dgm:dataModel>