<?xml version="1.0" encoding="UTF-8" standalone="yes"?>
<dgm:dataModel xmlns:dgm="http://schemas.openxmlformats.org/drawingml/2006/diagram" xmlns:a="http://schemas.openxmlformats.org/drawingml/2006/main"><dgm:ptLst><dgm:pt modelId="{6E2527ED-8951-4362-B7C5-4E8C28A820EE}" type="doc"><dgm:prSet loTypeId="urn:microsoft.com/office/officeart/2005/8/layout/equation2" loCatId="relationship" qsTypeId="urn:microsoft.com/office/officeart/2005/8/quickstyle/simple1" qsCatId="simple" csTypeId="urn:microsoft.com/office/officeart/2005/8/colors/accent1_2" csCatId="accent1" phldr="1"/><dgm:spPr/></dgm:pt><dgm:pt modelId="{F61E6624-D12A-4169-8D03-1C07721E6898}"><dgm:prSet phldrT="[Text]"/><dgm:spPr><a:solidFill><a:schemeClr val="accent4"/></a:solidFill></dgm:spPr><dgm:t><a:bodyPr/><a:lstStyle/><a:p><a:r><a:rPr lang="sv-SE"><a:solidFill><a:sysClr val="windowText" lastClr="000000"/></a:solidFill></a:rPr><a:t>Marna Månsdotter</a:t></a:r></a:p><a:p><a:r><a:rPr lang="sv-SE"><a:solidFill><a:sysClr val="windowText" lastClr="000000"/></a:solidFill></a:rPr><a:t>1841-1915</a:t></a:r></a:p></dgm:t></dgm:pt><dgm:pt modelId="{91FC6892-753E-4DF1-9939-9D3C9CDCF27A}" type="parTrans" cxnId="{609BACDE-0E61-489A-B5AB-DA8380D3A415}"><dgm:prSet/><dgm:spPr/><dgm:t><a:bodyPr/><a:lstStyle/><a:p><a:endParaRPr lang="sv-SE"/></a:p></dgm:t></dgm:pt><dgm:pt modelId="{1BF27CC8-B8E0-4918-B12D-9ECAE3225436}" type="sibTrans" cxnId="{609BACDE-0E61-489A-B5AB-DA8380D3A415}"><dgm:prSet/><dgm:spPr/><dgm:t><a:bodyPr/><a:lstStyle/><a:p><a:endParaRPr lang="sv-SE"/></a:p></dgm:t></dgm:pt><dgm:pt modelId="{D1200390-D45E-4828-A748-43302C02F257}"><dgm:prSet phldrT="[Text]"/><dgm:spPr><a:solidFill><a:schemeClr val="accent4"/></a:solidFill></dgm:spPr><dgm:t><a:bodyPr/><a:lstStyle/><a:p><a:r><a:rPr lang="sv-SE"><a:solidFill><a:sysClr val="windowText" lastClr="000000"/></a:solidFill></a:rPr><a:t>Jöns Nilsson</a:t></a:r></a:p><a:p><a:r><a:rPr lang="sv-SE"><a:solidFill><a:sysClr val="windowText" lastClr="000000"/></a:solidFill></a:rPr><a:t>1839-1915</a:t></a:r></a:p></dgm:t></dgm:pt><dgm:pt modelId="{F7E4AD34-00FB-4D0A-8BC8-9A3FD2240CCA}" type="parTrans" cxnId="{A7091205-DBBE-46C2-BE03-A71A3A567730}"><dgm:prSet/><dgm:spPr/><dgm:t><a:bodyPr/><a:lstStyle/><a:p><a:endParaRPr lang="sv-SE"/></a:p></dgm:t></dgm:pt><dgm:pt modelId="{E69249DF-B268-4188-9BEA-E0B9C7DFD3EA}" type="sibTrans" cxnId="{A7091205-DBBE-46C2-BE03-A71A3A567730}"><dgm:prSet/><dgm:spPr/><dgm:t><a:bodyPr/><a:lstStyle/><a:p><a:endParaRPr lang="sv-SE"/></a:p></dgm:t></dgm:pt><dgm:pt modelId="{26068042-CE33-486C-81E6-77BA6F2C9F67}"><dgm:prSet phldrT="[Text]"/><dgm:spPr><a:solidFill><a:schemeClr val="accent2"/></a:solidFill></dgm:spPr><dgm:t><a:bodyPr/><a:lstStyle/><a:p><a:r><a:rPr lang="sv-SE"/><a:t>Christina Jönsdotter</a:t></a:r></a:p><a:p><a:r><a:rPr lang="sv-SE"/><a:t>1866-1953</a:t></a:r></a:p></dgm:t></dgm:pt><dgm:pt modelId="{F9DCDBA7-637D-4D16-992B-FCC78D21E21C}" type="parTrans" cxnId="{0FD29921-3CF9-4F47-857E-15F89D8B3601}"><dgm:prSet/><dgm:spPr/><dgm:t><a:bodyPr/><a:lstStyle/><a:p><a:endParaRPr lang="sv-SE"/></a:p></dgm:t></dgm:pt><dgm:pt modelId="{0F6C2761-1155-4864-A950-5734DB94BAC3}" type="sibTrans" cxnId="{0FD29921-3CF9-4F47-857E-15F89D8B3601}"><dgm:prSet/><dgm:spPr/><dgm:t><a:bodyPr/><a:lstStyle/><a:p><a:endParaRPr lang="sv-SE"/></a:p></dgm:t></dgm:pt><dgm:pt modelId="{DDD65ED3-F2C5-4EEF-BEBC-214DBF79183B}" type="pres"><dgm:prSet presAssocID="{6E2527ED-8951-4362-B7C5-4E8C28A820EE}" presName="Name0" presStyleCnt="0"><dgm:presLayoutVars><dgm:dir/><dgm:resizeHandles val="exact"/></dgm:presLayoutVars></dgm:prSet><dgm:spPr/></dgm:pt><dgm:pt modelId="{2FBFCE0E-CD27-46B0-A931-C9B730E68A92}" type="pres"><dgm:prSet presAssocID="{6E2527ED-8951-4362-B7C5-4E8C28A820EE}" presName="vNodes" presStyleCnt="0"/><dgm:spPr/></dgm:pt><dgm:pt modelId="{CE952FCE-879F-49BD-8E09-C89D2BABAC51}" type="pres"><dgm:prSet presAssocID="{F61E6624-D12A-4169-8D03-1C07721E6898}" presName="node" presStyleLbl="node1" presStyleIdx="0" presStyleCnt="3"><dgm:presLayoutVars><dgm:bulletEnabled val="1"/></dgm:presLayoutVars></dgm:prSet><dgm:spPr/></dgm:pt><dgm:pt modelId="{61E0099C-A0C4-4F67-A8BA-F9D54164A5F5}" type="pres"><dgm:prSet presAssocID="{1BF27CC8-B8E0-4918-B12D-9ECAE3225436}" presName="spacerT" presStyleCnt="0"/><dgm:spPr/></dgm:pt><dgm:pt modelId="{215E4327-98C6-477D-BD73-2A61380E343B}" type="pres"><dgm:prSet presAssocID="{1BF27CC8-B8E0-4918-B12D-9ECAE3225436}" presName="sibTrans" presStyleLbl="sibTrans2D1" presStyleIdx="0" presStyleCnt="2"/><dgm:spPr/></dgm:pt><dgm:pt modelId="{A7866542-38DB-48CE-87EA-2C0CE597EC66}" type="pres"><dgm:prSet presAssocID="{1BF27CC8-B8E0-4918-B12D-9ECAE3225436}" presName="spacerB" presStyleCnt="0"/><dgm:spPr/></dgm:pt><dgm:pt modelId="{9449A000-B4F5-414A-BB58-77BF3CF0672E}" type="pres"><dgm:prSet presAssocID="{D1200390-D45E-4828-A748-43302C02F257}" presName="node" presStyleLbl="node1" presStyleIdx="1" presStyleCnt="3" custLinFactNeighborX="-1984" custLinFactNeighborY="-48873"><dgm:presLayoutVars><dgm:bulletEnabled val="1"/></dgm:presLayoutVars></dgm:prSet><dgm:spPr/></dgm:pt><dgm:pt modelId="{3F54DB5E-0726-4F47-87A2-8E7AE00918DB}" type="pres"><dgm:prSet presAssocID="{6E2527ED-8951-4362-B7C5-4E8C28A820EE}" presName="sibTransLast" presStyleLbl="sibTrans2D1" presStyleIdx="1" presStyleCnt="2"/><dgm:spPr/></dgm:pt><dgm:pt modelId="{A66AAD07-DAF2-4756-AD9E-EE584B0C3451}" type="pres"><dgm:prSet presAssocID="{6E2527ED-8951-4362-B7C5-4E8C28A820EE}" presName="connectorText" presStyleLbl="sibTrans2D1" presStyleIdx="1" presStyleCnt="2"/><dgm:spPr/></dgm:pt><dgm:pt modelId="{A66DA039-8BA5-4590-ACA2-ECE984B856AD}" type="pres"><dgm:prSet presAssocID="{6E2527ED-8951-4362-B7C5-4E8C28A820EE}" presName="lastNode" presStyleLbl="node1" presStyleIdx="2" presStyleCnt="3"><dgm:presLayoutVars><dgm:bulletEnabled val="1"/></dgm:presLayoutVars></dgm:prSet><dgm:spPr/></dgm:pt></dgm:ptLst><dgm:cxnLst><dgm:cxn modelId="{A7091205-DBBE-46C2-BE03-A71A3A567730}" srcId="{6E2527ED-8951-4362-B7C5-4E8C28A820EE}" destId="{D1200390-D45E-4828-A748-43302C02F257}" srcOrd="1" destOrd="0" parTransId="{F7E4AD34-00FB-4D0A-8BC8-9A3FD2240CCA}" sibTransId="{E69249DF-B268-4188-9BEA-E0B9C7DFD3EA}"/><dgm:cxn modelId="{F4EC0D17-C643-46E5-BC2E-614DB0579D62}" type="presOf" srcId="{F61E6624-D12A-4169-8D03-1C07721E6898}" destId="{CE952FCE-879F-49BD-8E09-C89D2BABAC51}" srcOrd="0" destOrd="0" presId="urn:microsoft.com/office/officeart/2005/8/layout/equation2"/><dgm:cxn modelId="{0FD29921-3CF9-4F47-857E-15F89D8B3601}" srcId="{6E2527ED-8951-4362-B7C5-4E8C28A820EE}" destId="{26068042-CE33-486C-81E6-77BA6F2C9F67}" srcOrd="2" destOrd="0" parTransId="{F9DCDBA7-637D-4D16-992B-FCC78D21E21C}" sibTransId="{0F6C2761-1155-4864-A950-5734DB94BAC3}"/><dgm:cxn modelId="{1FE99B35-CDD9-4F19-8D2C-62151C710A32}" type="presOf" srcId="{6E2527ED-8951-4362-B7C5-4E8C28A820EE}" destId="{DDD65ED3-F2C5-4EEF-BEBC-214DBF79183B}" srcOrd="0" destOrd="0" presId="urn:microsoft.com/office/officeart/2005/8/layout/equation2"/><dgm:cxn modelId="{07E34464-7F65-4CEF-A98C-636740107FA2}" type="presOf" srcId="{1BF27CC8-B8E0-4918-B12D-9ECAE3225436}" destId="{215E4327-98C6-477D-BD73-2A61380E343B}" srcOrd="0" destOrd="0" presId="urn:microsoft.com/office/officeart/2005/8/layout/equation2"/><dgm:cxn modelId="{5467B090-3BBF-4E87-B1C0-CE3BF2E3088E}" type="presOf" srcId="{E69249DF-B268-4188-9BEA-E0B9C7DFD3EA}" destId="{A66AAD07-DAF2-4756-AD9E-EE584B0C3451}" srcOrd="1" destOrd="0" presId="urn:microsoft.com/office/officeart/2005/8/layout/equation2"/><dgm:cxn modelId="{7105B49B-4BBE-4827-B312-0ECB7E21732A}" type="presOf" srcId="{D1200390-D45E-4828-A748-43302C02F257}" destId="{9449A000-B4F5-414A-BB58-77BF3CF0672E}" srcOrd="0" destOrd="0" presId="urn:microsoft.com/office/officeart/2005/8/layout/equation2"/><dgm:cxn modelId="{12DC2EDC-0818-4C4A-AC32-CF77CA2ABE03}" type="presOf" srcId="{E69249DF-B268-4188-9BEA-E0B9C7DFD3EA}" destId="{3F54DB5E-0726-4F47-87A2-8E7AE00918DB}" srcOrd="0" destOrd="0" presId="urn:microsoft.com/office/officeart/2005/8/layout/equation2"/><dgm:cxn modelId="{609BACDE-0E61-489A-B5AB-DA8380D3A415}" srcId="{6E2527ED-8951-4362-B7C5-4E8C28A820EE}" destId="{F61E6624-D12A-4169-8D03-1C07721E6898}" srcOrd="0" destOrd="0" parTransId="{91FC6892-753E-4DF1-9939-9D3C9CDCF27A}" sibTransId="{1BF27CC8-B8E0-4918-B12D-9ECAE3225436}"/><dgm:cxn modelId="{972FCAFF-4446-42FE-BBF7-EABD0E01A1D1}" type="presOf" srcId="{26068042-CE33-486C-81E6-77BA6F2C9F67}" destId="{A66DA039-8BA5-4590-ACA2-ECE984B856AD}" srcOrd="0" destOrd="0" presId="urn:microsoft.com/office/officeart/2005/8/layout/equation2"/><dgm:cxn modelId="{9C5D0B42-220E-4BBF-BCFD-677AD0941148}" type="presParOf" srcId="{DDD65ED3-F2C5-4EEF-BEBC-214DBF79183B}" destId="{2FBFCE0E-CD27-46B0-A931-C9B730E68A92}" srcOrd="0" destOrd="0" presId="urn:microsoft.com/office/officeart/2005/8/layout/equation2"/><dgm:cxn modelId="{AC89B19D-357D-4A19-9E01-CF6736F1DF16}" type="presParOf" srcId="{2FBFCE0E-CD27-46B0-A931-C9B730E68A92}" destId="{CE952FCE-879F-49BD-8E09-C89D2BABAC51}" srcOrd="0" destOrd="0" presId="urn:microsoft.com/office/officeart/2005/8/layout/equation2"/><dgm:cxn modelId="{5252AFCB-D751-40A6-876D-CC2B41D0EBA1}" type="presParOf" srcId="{2FBFCE0E-CD27-46B0-A931-C9B730E68A92}" destId="{61E0099C-A0C4-4F67-A8BA-F9D54164A5F5}" srcOrd="1" destOrd="0" presId="urn:microsoft.com/office/officeart/2005/8/layout/equation2"/><dgm:cxn modelId="{F07B49A6-0209-46AF-8A00-D8AC9F26FEF5}" type="presParOf" srcId="{2FBFCE0E-CD27-46B0-A931-C9B730E68A92}" destId="{215E4327-98C6-477D-BD73-2A61380E343B}" srcOrd="2" destOrd="0" presId="urn:microsoft.com/office/officeart/2005/8/layout/equation2"/><dgm:cxn modelId="{79F81A2D-E726-4117-954A-22D21F9BC5C6}" type="presParOf" srcId="{2FBFCE0E-CD27-46B0-A931-C9B730E68A92}" destId="{A7866542-38DB-48CE-87EA-2C0CE597EC66}" srcOrd="3" destOrd="0" presId="urn:microsoft.com/office/officeart/2005/8/layout/equation2"/><dgm:cxn modelId="{304F55B4-0E23-414D-B5BC-98744B302DE8}" type="presParOf" srcId="{2FBFCE0E-CD27-46B0-A931-C9B730E68A92}" destId="{9449A000-B4F5-414A-BB58-77BF3CF0672E}" srcOrd="4" destOrd="0" presId="urn:microsoft.com/office/officeart/2005/8/layout/equation2"/><dgm:cxn modelId="{7C2BB92E-1CCA-4683-BE6F-CFF8BABE9C8C}" type="presParOf" srcId="{DDD65ED3-F2C5-4EEF-BEBC-214DBF79183B}" destId="{3F54DB5E-0726-4F47-87A2-8E7AE00918DB}" srcOrd="1" destOrd="0" presId="urn:microsoft.com/office/officeart/2005/8/layout/equation2"/><dgm:cxn modelId="{4B7AAE66-62F5-4B5D-B49D-735EA0EECCE2}" type="presParOf" srcId="{3F54DB5E-0726-4F47-87A2-8E7AE00918DB}" destId="{A66AAD07-DAF2-4756-AD9E-EE584B0C3451}" srcOrd="0" destOrd="0" presId="urn:microsoft.com/office/officeart/2005/8/layout/equation2"/><dgm:cxn modelId="{858211C2-303A-4294-9039-C78B645C443D}" type="presParOf" srcId="{DDD65ED3-F2C5-4EEF-BEBC-214DBF79183B}" destId="{A66DA039-8BA5-4590-ACA2-ECE984B856AD}" srcOrd="2" destOrd="0" presId="urn:microsoft.com/office/officeart/2005/8/layout/equation2"/></dgm:cxnLst><dgm:bg/><dgm:whole/><dgm:extLst><a:ext uri="http://schemas.microsoft.com/office/drawing/2008/diagram"><dsp:dataModelExt xmlns:dsp="http://schemas.microsoft.com/office/drawing/2008/diagram" relId="rId589" minVer="http://schemas.openxmlformats.org/drawingml/2006/diagram"/></a:ext></dgm:extLst></dgm:dataModel>