<?xml version="1.0" encoding="UTF-8" standalone="yes"?>
<dgm:dataModel xmlns:dgm="http://schemas.openxmlformats.org/drawingml/2006/diagram" xmlns:a="http://schemas.openxmlformats.org/drawingml/2006/main"><dgm:ptLst><dgm:pt modelId="{A96E9E58-1A5E-4BB9-AE14-E44A1CD64E45}" type="doc"><dgm:prSet loTypeId="urn:microsoft.com/office/officeart/2005/8/layout/hierarchy1" loCatId="hierarchy" qsTypeId="urn:microsoft.com/office/officeart/2005/8/quickstyle/simple1" qsCatId="simple" csTypeId="urn:microsoft.com/office/officeart/2005/8/colors/accent1_2" csCatId="accent1" phldr="1"/><dgm:spPr/><dgm:t><a:bodyPr/><a:lstStyle/><a:p><a:endParaRPr lang="sv-SE"/></a:p></dgm:t></dgm:pt><dgm:pt modelId="{E76F06C7-BB5C-415B-BDAE-38A0DBDD95D9}"><dgm:prSet phldrT="[Text]"/><dgm:spPr/><dgm:t><a:bodyPr/><a:lstStyle/><a:p><a:pPr algn="ctr"/><a:r><a:rPr lang="sv-SE"/><a:t>Peter Bengtsson Alin</a:t></a:r></a:p><a:p><a:pPr algn="ctr"/><a:r><a:rPr lang="sv-SE"/><a:t>1859-1933</a:t></a:r></a:p></dgm:t></dgm:pt><dgm:pt modelId="{61981EB0-B651-4EAC-8E55-D76B8460F4D7}" type="parTrans" cxnId="{CA6487C3-47F8-4154-A034-459EED42576B}"><dgm:prSet/><dgm:spPr/><dgm:t><a:bodyPr/><a:lstStyle/><a:p><a:pPr algn="ctr"/><a:endParaRPr lang="sv-SE"/></a:p></dgm:t></dgm:pt><dgm:pt modelId="{4AB4D94D-8F15-4480-8CAE-BE949D7A7DD2}" type="sibTrans" cxnId="{CA6487C3-47F8-4154-A034-459EED42576B}"><dgm:prSet/><dgm:spPr/><dgm:t><a:bodyPr/><a:lstStyle/><a:p><a:pPr algn="ctr"/><a:endParaRPr lang="sv-SE"/></a:p></dgm:t></dgm:pt><dgm:pt modelId="{4B3C98DA-860F-4098-A26A-812D56B96FE3}"><dgm:prSet phldrT="[Text]"/><dgm:spPr/><dgm:t><a:bodyPr/><a:lstStyle/><a:p><a:pPr algn="ctr"/><a:r><a:rPr lang="sv-SE"/><a:t>Kerstin Jönsdotter</a:t></a:r></a:p><a:p><a:pPr algn="ctr"/><a:r><a:rPr lang="sv-SE"/><a:t>1820-1869</a:t></a:r></a:p></dgm:t></dgm:pt><dgm:pt modelId="{D7A1B228-CBCA-4026-AAD5-F680D9FB6214}" type="parTrans" cxnId="{299B5B44-73EF-472A-9A20-452E685B02D1}"><dgm:prSet/><dgm:spPr/><dgm:t><a:bodyPr/><a:lstStyle/><a:p><a:pPr algn="ctr"/><a:endParaRPr lang="sv-SE"/></a:p></dgm:t></dgm:pt><dgm:pt modelId="{C037B149-D302-4A19-B00E-68317EEEC897}" type="sibTrans" cxnId="{299B5B44-73EF-472A-9A20-452E685B02D1}"><dgm:prSet/><dgm:spPr/><dgm:t><a:bodyPr/><a:lstStyle/><a:p><a:pPr algn="ctr"/><a:endParaRPr lang="sv-SE"/></a:p></dgm:t></dgm:pt><dgm:pt modelId="{05BDFADE-6B6F-4D19-98E0-6ACAEB9649B4}"><dgm:prSet phldrT="[Text]"/><dgm:spPr/><dgm:t><a:bodyPr/><a:lstStyle/><a:p><a:pPr algn="ctr"/><a:r><a:rPr lang="sv-SE"/><a:t>Bengt Nordqvist</a:t></a:r></a:p><a:p><a:pPr algn="ctr"/><a:r><a:rPr lang="sv-SE"/><a:t>1826-1904</a:t></a:r></a:p></dgm:t></dgm:pt><dgm:pt modelId="{6C6D8593-343D-4604-8053-5ECF3A36871A}" type="parTrans" cxnId="{69C79EA0-D5D2-41B8-B53B-CCA6393876B5}"><dgm:prSet/><dgm:spPr/><dgm:t><a:bodyPr/><a:lstStyle/><a:p><a:pPr algn="ctr"/><a:endParaRPr lang="sv-SE"/></a:p></dgm:t></dgm:pt><dgm:pt modelId="{DB30FD50-4436-4A47-A24F-7492AAE34863}" type="sibTrans" cxnId="{69C79EA0-D5D2-41B8-B53B-CCA6393876B5}"><dgm:prSet/><dgm:spPr/><dgm:t><a:bodyPr/><a:lstStyle/><a:p><a:pPr algn="ctr"/><a:endParaRPr lang="sv-SE"/></a:p></dgm:t></dgm:pt><dgm:pt modelId="{DD98DB28-CA2B-4A19-99B3-1C1F6085434A}"><dgm:prSet phldrT="[Text]"/><dgm:spPr/><dgm:t><a:bodyPr/><a:lstStyle/><a:p><a:pPr algn="ctr"/><a:r><a:rPr lang="sv-SE"/><a:t>Gunnil Danielsdotter</a:t></a:r></a:p><a:p><a:pPr algn="ctr"/><a:r><a:rPr lang="sv-SE"/><a:t>1783-1861</a:t></a:r></a:p></dgm:t></dgm:pt><dgm:pt modelId="{A6CBA7F9-CB2A-42C1-9FE4-9EAFFEC75D12}" type="parTrans" cxnId="{05611C05-D6E2-4E7D-A7F7-1060B863B584}"><dgm:prSet/><dgm:spPr/><dgm:t><a:bodyPr/><a:lstStyle/><a:p><a:pPr algn="ctr"/><a:endParaRPr lang="sv-SE"/></a:p></dgm:t></dgm:pt><dgm:pt modelId="{F31179F2-E126-4C3C-8442-C7BEC8BE37C2}" type="sibTrans" cxnId="{05611C05-D6E2-4E7D-A7F7-1060B863B584}"><dgm:prSet/><dgm:spPr/><dgm:t><a:bodyPr/><a:lstStyle/><a:p><a:pPr algn="ctr"/><a:endParaRPr lang="sv-SE"/></a:p></dgm:t></dgm:pt><dgm:pt modelId="{02F41359-2000-4693-B51C-D967970F9871}"><dgm:prSet/><dgm:spPr/><dgm:t><a:bodyPr/><a:lstStyle/><a:p><a:pPr algn="ctr"/><a:r><a:rPr lang="sv-SE"/><a:t>Per Ingemansson</a:t></a:r></a:p><a:p><a:pPr algn="ctr"/><a:r><a:rPr lang="sv-SE"/><a:t>1783-1836</a:t></a:r></a:p></dgm:t></dgm:pt><dgm:pt modelId="{193F5744-2EB9-42B6-9B29-5BD876DA8A15}" type="parTrans" cxnId="{374AE921-4180-4C72-BC36-A3B44D8803C8}"><dgm:prSet/><dgm:spPr/><dgm:t><a:bodyPr/><a:lstStyle/><a:p><a:pPr algn="ctr"/><a:endParaRPr lang="sv-SE"/></a:p></dgm:t></dgm:pt><dgm:pt modelId="{FAA884DF-D7AB-45D7-A43A-AFEC95F3C97F}" type="sibTrans" cxnId="{374AE921-4180-4C72-BC36-A3B44D8803C8}"><dgm:prSet/><dgm:spPr/><dgm:t><a:bodyPr/><a:lstStyle/><a:p><a:pPr algn="ctr"/><a:endParaRPr lang="sv-SE"/></a:p></dgm:t></dgm:pt><dgm:pt modelId="{68C4B14F-3DED-4A9C-A5AC-313677F26E4F}"><dgm:prSet/><dgm:spPr/><dgm:t><a:bodyPr/><a:lstStyle/><a:p><a:pPr algn="ctr"/><a:r><a:rPr lang="sv-SE"/><a:t>Stina Ambjörnsdotter</a:t></a:r></a:p><a:p><a:pPr algn="ctr"/><a:r><a:rPr lang="sv-SE"/><a:t>1736-1823</a:t></a:r></a:p></dgm:t></dgm:pt><dgm:pt modelId="{26AAA6C6-3DAE-4739-8959-6FC98F7D7238}" type="parTrans" cxnId="{AED03D14-9C2E-4698-B498-A239DC4575CC}"><dgm:prSet/><dgm:spPr/><dgm:t><a:bodyPr/><a:lstStyle/><a:p><a:pPr algn="ctr"/><a:endParaRPr lang="sv-SE"/></a:p></dgm:t></dgm:pt><dgm:pt modelId="{7C98A040-E3CE-4BF2-9108-8E6D6AD58D18}" type="sibTrans" cxnId="{AED03D14-9C2E-4698-B498-A239DC4575CC}"><dgm:prSet/><dgm:spPr/><dgm:t><a:bodyPr/><a:lstStyle/><a:p><a:pPr algn="ctr"/><a:endParaRPr lang="sv-SE"/></a:p></dgm:t></dgm:pt><dgm:pt modelId="{FB46E635-D183-4F54-8BA4-9110B2596327}"><dgm:prSet/><dgm:spPr/><dgm:t><a:bodyPr/><a:lstStyle/><a:p><a:pPr algn="ctr"/><a:r><a:rPr lang="sv-SE"/><a:t>Ingeman Dufva</a:t></a:r></a:p><a:p><a:pPr algn="ctr"/><a:r><a:rPr lang="sv-SE"/><a:t>1749-1789</a:t></a:r></a:p></dgm:t></dgm:pt><dgm:pt modelId="{B559931F-0554-4F1D-80F8-163E8A3E72B8}" type="parTrans" cxnId="{81C689C8-949F-4558-BE61-7FDBA8143A95}"><dgm:prSet/><dgm:spPr/><dgm:t><a:bodyPr/><a:lstStyle/><a:p><a:pPr algn="ctr"/><a:endParaRPr lang="sv-SE"/></a:p></dgm:t></dgm:pt><dgm:pt modelId="{D063BEA2-BFC1-4AEC-BDA1-F403A9141D03}" type="sibTrans" cxnId="{81C689C8-949F-4558-BE61-7FDBA8143A95}"><dgm:prSet/><dgm:spPr/><dgm:t><a:bodyPr/><a:lstStyle/><a:p><a:pPr algn="ctr"/><a:endParaRPr lang="sv-SE"/></a:p></dgm:t></dgm:pt><dgm:pt modelId="{67A9F40C-B22D-45C5-8B1B-AB3F98EBB3DE}"><dgm:prSet/><dgm:spPr/><dgm:t><a:bodyPr/><a:lstStyle/><a:p><a:pPr algn="ctr"/><a:r><a:rPr lang="sv-SE"/><a:t>Daniel Persson</a:t></a:r></a:p><a:p><a:pPr algn="ctr"/><a:r><a:rPr lang="sv-SE"/><a:t>1744-1818</a:t></a:r></a:p></dgm:t></dgm:pt><dgm:pt modelId="{A777C4DF-5FCC-4D66-8D77-B564D2682045}" type="parTrans" cxnId="{C9653809-6B59-4C54-92DC-A8884B116B17}"><dgm:prSet/><dgm:spPr/><dgm:t><a:bodyPr/><a:lstStyle/><a:p><a:pPr algn="ctr"/><a:endParaRPr lang="sv-SE"/></a:p></dgm:t></dgm:pt><dgm:pt modelId="{1263A584-A52B-4B65-83EF-0C9F5678DD02}" type="sibTrans" cxnId="{C9653809-6B59-4C54-92DC-A8884B116B17}"><dgm:prSet/><dgm:spPr/><dgm:t><a:bodyPr/><a:lstStyle/><a:p><a:pPr algn="ctr"/><a:endParaRPr lang="sv-SE"/></a:p></dgm:t></dgm:pt><dgm:pt modelId="{86E60FF7-EBD9-49C9-B604-08A63D05DEC8}"><dgm:prSet/><dgm:spPr/><dgm:t><a:bodyPr/><a:lstStyle/><a:p><a:pPr algn="ctr"/><a:r><a:rPr lang="sv-SE"/><a:t>Bereta Jönsdotter</a:t></a:r></a:p><a:p><a:pPr algn="ctr"/><a:r><a:rPr lang="sv-SE"/><a:t>1741-1798</a:t></a:r></a:p></dgm:t></dgm:pt><dgm:pt modelId="{B4386F82-6DBA-4CD9-BCDF-F17AAFB1216B}" type="parTrans" cxnId="{398FB98F-DC57-4B5E-A149-4C5B2F2829E3}"><dgm:prSet/><dgm:spPr/><dgm:t><a:bodyPr/><a:lstStyle/><a:p><a:pPr algn="ctr"/><a:endParaRPr lang="sv-SE"/></a:p></dgm:t></dgm:pt><dgm:pt modelId="{2E1F1054-5F65-4FF4-9C60-C33979D0E2A7}" type="sibTrans" cxnId="{398FB98F-DC57-4B5E-A149-4C5B2F2829E3}"><dgm:prSet/><dgm:spPr/><dgm:t><a:bodyPr/><a:lstStyle/><a:p><a:pPr algn="ctr"/><a:endParaRPr lang="sv-SE"/></a:p></dgm:t></dgm:pt><dgm:pt modelId="{30E72103-622E-4ACB-BB4F-9A636E26B64D}" type="pres"><dgm:prSet presAssocID="{A96E9E58-1A5E-4BB9-AE14-E44A1CD64E45}" presName="hierChild1" presStyleCnt="0"><dgm:presLayoutVars><dgm:chPref val="1"/><dgm:dir/><dgm:animOne val="branch"/><dgm:animLvl val="lvl"/><dgm:resizeHandles/></dgm:presLayoutVars></dgm:prSet><dgm:spPr/></dgm:pt><dgm:pt modelId="{1646D6ED-3346-445B-8D04-73973487F8C7}" type="pres"><dgm:prSet presAssocID="{E76F06C7-BB5C-415B-BDAE-38A0DBDD95D9}" presName="hierRoot1" presStyleCnt="0"/><dgm:spPr/></dgm:pt><dgm:pt modelId="{2A76C565-2D05-47DB-90BA-AD4D577F949A}" type="pres"><dgm:prSet presAssocID="{E76F06C7-BB5C-415B-BDAE-38A0DBDD95D9}" presName="composite" presStyleCnt="0"/><dgm:spPr/></dgm:pt><dgm:pt modelId="{98EA51C6-BB0E-4BBB-8987-F50B0E13E36C}" type="pres"><dgm:prSet presAssocID="{E76F06C7-BB5C-415B-BDAE-38A0DBDD95D9}" presName="background" presStyleLbl="node0" presStyleIdx="0" presStyleCnt="1"/><dgm:spPr><a:solidFill><a:srgbClr val="4F81BD"/></a:solidFill></dgm:spPr></dgm:pt><dgm:pt modelId="{66EFAB48-B846-4945-A919-92AD5F3E65F0}" type="pres"><dgm:prSet presAssocID="{E76F06C7-BB5C-415B-BDAE-38A0DBDD95D9}" presName="text" presStyleLbl="fgAcc0" presStyleIdx="0" presStyleCnt="1"><dgm:presLayoutVars><dgm:chPref val="3"/></dgm:presLayoutVars></dgm:prSet><dgm:spPr/></dgm:pt><dgm:pt modelId="{947BD69F-2735-4826-957D-D3A159246506}" type="pres"><dgm:prSet presAssocID="{E76F06C7-BB5C-415B-BDAE-38A0DBDD95D9}" presName="hierChild2" presStyleCnt="0"/><dgm:spPr/></dgm:pt><dgm:pt modelId="{ED9BEC03-655F-4B72-8B6D-866E2222F1B1}" type="pres"><dgm:prSet presAssocID="{D7A1B228-CBCA-4026-AAD5-F680D9FB6214}" presName="Name10" presStyleLbl="parChTrans1D2" presStyleIdx="0" presStyleCnt="2"/><dgm:spPr/></dgm:pt><dgm:pt modelId="{288D2679-5CAC-4A07-A0E7-D635C4A2F766}" type="pres"><dgm:prSet presAssocID="{4B3C98DA-860F-4098-A26A-812D56B96FE3}" presName="hierRoot2" presStyleCnt="0"/><dgm:spPr/></dgm:pt><dgm:pt modelId="{8309DB3B-8F84-4843-BDFD-CD3EDA2EBA64}" type="pres"><dgm:prSet presAssocID="{4B3C98DA-860F-4098-A26A-812D56B96FE3}" presName="composite2" presStyleCnt="0"/><dgm:spPr/></dgm:pt><dgm:pt modelId="{7D8D35D9-1812-4729-A852-740D72BB4BDE}" type="pres"><dgm:prSet presAssocID="{4B3C98DA-860F-4098-A26A-812D56B96FE3}" presName="background2" presStyleLbl="node2" presStyleIdx="0" presStyleCnt="2"/><dgm:spPr><a:solidFill><a:schemeClr val="accent2"><a:lumMod val="75000"/></a:schemeClr></a:solidFill></dgm:spPr></dgm:pt><dgm:pt modelId="{CA59AF42-B5D3-474D-9E4F-45BF6E07B1B8}" type="pres"><dgm:prSet presAssocID="{4B3C98DA-860F-4098-A26A-812D56B96FE3}" presName="text2" presStyleLbl="fgAcc2" presStyleIdx="0" presStyleCnt="2"><dgm:presLayoutVars><dgm:chPref val="3"/></dgm:presLayoutVars></dgm:prSet><dgm:spPr/></dgm:pt><dgm:pt modelId="{E2296C62-622F-4DA1-AE18-38FF9E99676E}" type="pres"><dgm:prSet presAssocID="{4B3C98DA-860F-4098-A26A-812D56B96FE3}" presName="hierChild3" presStyleCnt="0"/><dgm:spPr/></dgm:pt><dgm:pt modelId="{EB4B47D3-78C9-4A29-8831-253E60AB2C95}" type="pres"><dgm:prSet presAssocID="{6C6D8593-343D-4604-8053-5ECF3A36871A}" presName="Name10" presStyleLbl="parChTrans1D2" presStyleIdx="1" presStyleCnt="2"/><dgm:spPr/></dgm:pt><dgm:pt modelId="{1D6866E3-A80C-473C-A05E-D946ADDB3DD8}" type="pres"><dgm:prSet presAssocID="{05BDFADE-6B6F-4D19-98E0-6ACAEB9649B4}" presName="hierRoot2" presStyleCnt="0"/><dgm:spPr/></dgm:pt><dgm:pt modelId="{145FAFC4-CB1D-4556-B216-957535E47B91}" type="pres"><dgm:prSet presAssocID="{05BDFADE-6B6F-4D19-98E0-6ACAEB9649B4}" presName="composite2" presStyleCnt="0"/><dgm:spPr/></dgm:pt><dgm:pt modelId="{05C36326-416D-49BE-9197-E5D8C34C6C47}" type="pres"><dgm:prSet presAssocID="{05BDFADE-6B6F-4D19-98E0-6ACAEB9649B4}" presName="background2" presStyleLbl="node2" presStyleIdx="1" presStyleCnt="2"/><dgm:spPr><a:solidFill><a:schemeClr val="accent2"><a:lumMod val="75000"/></a:schemeClr></a:solidFill></dgm:spPr></dgm:pt><dgm:pt modelId="{1187A332-BE58-497C-B62A-E67BD2F7CA03}" type="pres"><dgm:prSet presAssocID="{05BDFADE-6B6F-4D19-98E0-6ACAEB9649B4}" presName="text2" presStyleLbl="fgAcc2" presStyleIdx="1" presStyleCnt="2"><dgm:presLayoutVars><dgm:chPref val="3"/></dgm:presLayoutVars></dgm:prSet><dgm:spPr/></dgm:pt><dgm:pt modelId="{918E4B51-D1C3-438F-BC8A-983398D37926}" type="pres"><dgm:prSet presAssocID="{05BDFADE-6B6F-4D19-98E0-6ACAEB9649B4}" presName="hierChild3" presStyleCnt="0"/><dgm:spPr/></dgm:pt><dgm:pt modelId="{61C43B60-00B9-4137-93C9-E6549E07BA5C}" type="pres"><dgm:prSet presAssocID="{A6CBA7F9-CB2A-42C1-9FE4-9EAFFEC75D12}" presName="Name17" presStyleLbl="parChTrans1D3" presStyleIdx="0" presStyleCnt="2"/><dgm:spPr/></dgm:pt><dgm:pt modelId="{C40041AA-B6AD-4498-B8E6-7B97E19E427B}" type="pres"><dgm:prSet presAssocID="{DD98DB28-CA2B-4A19-99B3-1C1F6085434A}" presName="hierRoot3" presStyleCnt="0"/><dgm:spPr/></dgm:pt><dgm:pt modelId="{69B18AE8-1D52-4824-95F7-9D0BFC9E926F}" type="pres"><dgm:prSet presAssocID="{DD98DB28-CA2B-4A19-99B3-1C1F6085434A}" presName="composite3" presStyleCnt="0"/><dgm:spPr/></dgm:pt><dgm:pt modelId="{FC7B7AB0-041A-4648-AF06-E2BFCE5DC72E}" type="pres"><dgm:prSet presAssocID="{DD98DB28-CA2B-4A19-99B3-1C1F6085434A}" presName="background3" presStyleLbl="node3" presStyleIdx="0" presStyleCnt="2"/><dgm:spPr><a:solidFill><a:schemeClr val="accent2"/></a:solidFill></dgm:spPr></dgm:pt><dgm:pt modelId="{BEAD8990-338B-4972-9DC9-5297E63253C1}" type="pres"><dgm:prSet presAssocID="{DD98DB28-CA2B-4A19-99B3-1C1F6085434A}" presName="text3" presStyleLbl="fgAcc3" presStyleIdx="0" presStyleCnt="2"><dgm:presLayoutVars><dgm:chPref val="3"/></dgm:presLayoutVars></dgm:prSet><dgm:spPr/></dgm:pt><dgm:pt modelId="{1170EE48-69DA-4684-BAFE-1636523EEF8B}" type="pres"><dgm:prSet presAssocID="{DD98DB28-CA2B-4A19-99B3-1C1F6085434A}" presName="hierChild4" presStyleCnt="0"/><dgm:spPr/></dgm:pt><dgm:pt modelId="{36A0FDEF-9C80-44BF-B9C9-963DE8FF2ABD}" type="pres"><dgm:prSet presAssocID="{B4386F82-6DBA-4CD9-BCDF-F17AAFB1216B}" presName="Name23" presStyleLbl="parChTrans1D4" presStyleIdx="0" presStyleCnt="4"/><dgm:spPr/></dgm:pt><dgm:pt modelId="{49ACFE62-E98F-4F23-8522-9519C1EDFC9C}" type="pres"><dgm:prSet presAssocID="{86E60FF7-EBD9-49C9-B604-08A63D05DEC8}" presName="hierRoot4" presStyleCnt="0"/><dgm:spPr/></dgm:pt><dgm:pt modelId="{FBB4F7F3-FDFD-4C7A-B357-BE66D7324673}" type="pres"><dgm:prSet presAssocID="{86E60FF7-EBD9-49C9-B604-08A63D05DEC8}" presName="composite4" presStyleCnt="0"/><dgm:spPr/></dgm:pt><dgm:pt modelId="{99E54DB5-A07A-4C23-9E88-AD6FFFC64D29}" type="pres"><dgm:prSet presAssocID="{86E60FF7-EBD9-49C9-B604-08A63D05DEC8}" presName="background4" presStyleLbl="node4" presStyleIdx="0" presStyleCnt="4"/><dgm:spPr><a:solidFill><a:srgbClr val="FFC000"/></a:solidFill></dgm:spPr></dgm:pt><dgm:pt modelId="{BA344F40-DA45-4713-8AA1-6D47DB5F0C83}" type="pres"><dgm:prSet presAssocID="{86E60FF7-EBD9-49C9-B604-08A63D05DEC8}" presName="text4" presStyleLbl="fgAcc4" presStyleIdx="0" presStyleCnt="4"><dgm:presLayoutVars><dgm:chPref val="3"/></dgm:presLayoutVars></dgm:prSet><dgm:spPr/></dgm:pt><dgm:pt modelId="{C91886EF-1172-4FF2-B434-958FAC969DF1}" type="pres"><dgm:prSet presAssocID="{86E60FF7-EBD9-49C9-B604-08A63D05DEC8}" presName="hierChild5" presStyleCnt="0"/><dgm:spPr/></dgm:pt><dgm:pt modelId="{FA728B40-8594-4EE3-AEF0-42F442E6CF53}" type="pres"><dgm:prSet presAssocID="{A777C4DF-5FCC-4D66-8D77-B564D2682045}" presName="Name23" presStyleLbl="parChTrans1D4" presStyleIdx="1" presStyleCnt="4"/><dgm:spPr/></dgm:pt><dgm:pt modelId="{A75D6FC5-BBA8-431C-B840-91B6FFAFA1C9}" type="pres"><dgm:prSet presAssocID="{67A9F40C-B22D-45C5-8B1B-AB3F98EBB3DE}" presName="hierRoot4" presStyleCnt="0"/><dgm:spPr/></dgm:pt><dgm:pt modelId="{F4478BCD-E641-4D5E-873B-FEB04C50F7DB}" type="pres"><dgm:prSet presAssocID="{67A9F40C-B22D-45C5-8B1B-AB3F98EBB3DE}" presName="composite4" presStyleCnt="0"/><dgm:spPr/></dgm:pt><dgm:pt modelId="{D6A8E232-1D6E-41B1-AA98-A69997EDBE47}" type="pres"><dgm:prSet presAssocID="{67A9F40C-B22D-45C5-8B1B-AB3F98EBB3DE}" presName="background4" presStyleLbl="node4" presStyleIdx="1" presStyleCnt="4"/><dgm:spPr><a:solidFill><a:srgbClr val="FFC000"/></a:solidFill></dgm:spPr></dgm:pt><dgm:pt modelId="{A1347397-5D99-4DCE-9F90-3FCEF6D40048}" type="pres"><dgm:prSet presAssocID="{67A9F40C-B22D-45C5-8B1B-AB3F98EBB3DE}" presName="text4" presStyleLbl="fgAcc4" presStyleIdx="1" presStyleCnt="4"><dgm:presLayoutVars><dgm:chPref val="3"/></dgm:presLayoutVars></dgm:prSet><dgm:spPr/></dgm:pt><dgm:pt modelId="{33A4A662-AE4A-463B-9B1C-E950C1FE1E0F}" type="pres"><dgm:prSet presAssocID="{67A9F40C-B22D-45C5-8B1B-AB3F98EBB3DE}" presName="hierChild5" presStyleCnt="0"/><dgm:spPr/></dgm:pt><dgm:pt modelId="{14059B0E-1C24-430B-8153-F310BF4A40A3}" type="pres"><dgm:prSet presAssocID="{193F5744-2EB9-42B6-9B29-5BD876DA8A15}" presName="Name17" presStyleLbl="parChTrans1D3" presStyleIdx="1" presStyleCnt="2"/><dgm:spPr/></dgm:pt><dgm:pt modelId="{31763496-D517-4508-9333-8D4DF4BFD4E0}" type="pres"><dgm:prSet presAssocID="{02F41359-2000-4693-B51C-D967970F9871}" presName="hierRoot3" presStyleCnt="0"/><dgm:spPr/></dgm:pt><dgm:pt modelId="{EEFA94E9-BF9D-44E2-A4CF-6E698545178C}" type="pres"><dgm:prSet presAssocID="{02F41359-2000-4693-B51C-D967970F9871}" presName="composite3" presStyleCnt="0"/><dgm:spPr/></dgm:pt><dgm:pt modelId="{1639B34E-E530-43D4-92B0-CBB06896CDCD}" type="pres"><dgm:prSet presAssocID="{02F41359-2000-4693-B51C-D967970F9871}" presName="background3" presStyleLbl="node3" presStyleIdx="1" presStyleCnt="2"/><dgm:spPr><a:solidFill><a:srgbClr val="ED7D31"/></a:solidFill></dgm:spPr></dgm:pt><dgm:pt modelId="{252360A4-7143-4832-B1D6-16B6DB19483C}" type="pres"><dgm:prSet presAssocID="{02F41359-2000-4693-B51C-D967970F9871}" presName="text3" presStyleLbl="fgAcc3" presStyleIdx="1" presStyleCnt="2"><dgm:presLayoutVars><dgm:chPref val="3"/></dgm:presLayoutVars></dgm:prSet><dgm:spPr/></dgm:pt><dgm:pt modelId="{CE05A8D0-8B70-406D-93DF-17554536A2C0}" type="pres"><dgm:prSet presAssocID="{02F41359-2000-4693-B51C-D967970F9871}" presName="hierChild4" presStyleCnt="0"/><dgm:spPr/></dgm:pt><dgm:pt modelId="{59F2ED9D-EEDE-4E12-8072-0E20DE4B1984}" type="pres"><dgm:prSet presAssocID="{26AAA6C6-3DAE-4739-8959-6FC98F7D7238}" presName="Name23" presStyleLbl="parChTrans1D4" presStyleIdx="2" presStyleCnt="4"/><dgm:spPr/></dgm:pt><dgm:pt modelId="{9EF8BDCF-0B01-4690-8A60-A63831CC83EB}" type="pres"><dgm:prSet presAssocID="{68C4B14F-3DED-4A9C-A5AC-313677F26E4F}" presName="hierRoot4" presStyleCnt="0"/><dgm:spPr/></dgm:pt><dgm:pt modelId="{8ED8A936-42DB-46F9-9751-D64C2969B269}" type="pres"><dgm:prSet presAssocID="{68C4B14F-3DED-4A9C-A5AC-313677F26E4F}" presName="composite4" presStyleCnt="0"/><dgm:spPr/></dgm:pt><dgm:pt modelId="{80A8E217-4055-4BD3-9111-BD3FD28D2F74}" type="pres"><dgm:prSet presAssocID="{68C4B14F-3DED-4A9C-A5AC-313677F26E4F}" presName="background4" presStyleLbl="node4" presStyleIdx="2" presStyleCnt="4"/><dgm:spPr><a:solidFill><a:srgbClr val="9BBB59"/></a:solidFill></dgm:spPr></dgm:pt><dgm:pt modelId="{A457F630-2A04-4DEA-8698-6A3F471ECBD7}" type="pres"><dgm:prSet presAssocID="{68C4B14F-3DED-4A9C-A5AC-313677F26E4F}" presName="text4" presStyleLbl="fgAcc4" presStyleIdx="2" presStyleCnt="4"><dgm:presLayoutVars><dgm:chPref val="3"/></dgm:presLayoutVars></dgm:prSet><dgm:spPr/></dgm:pt><dgm:pt modelId="{C913EE18-0A66-4209-95A5-804DCA3FDED9}" type="pres"><dgm:prSet presAssocID="{68C4B14F-3DED-4A9C-A5AC-313677F26E4F}" presName="hierChild5" presStyleCnt="0"/><dgm:spPr/></dgm:pt><dgm:pt modelId="{F276219D-E0D2-49A4-86FC-71103CE17672}" type="pres"><dgm:prSet presAssocID="{B559931F-0554-4F1D-80F8-163E8A3E72B8}" presName="Name23" presStyleLbl="parChTrans1D4" presStyleIdx="3" presStyleCnt="4"/><dgm:spPr/></dgm:pt><dgm:pt modelId="{E8A540F5-EC80-4CD5-94E6-BCA1AA33D54A}" type="pres"><dgm:prSet presAssocID="{FB46E635-D183-4F54-8BA4-9110B2596327}" presName="hierRoot4" presStyleCnt="0"/><dgm:spPr/></dgm:pt><dgm:pt modelId="{289ADCB4-A6A6-43BB-B38D-1DFC6E25B831}" type="pres"><dgm:prSet presAssocID="{FB46E635-D183-4F54-8BA4-9110B2596327}" presName="composite4" presStyleCnt="0"/><dgm:spPr/></dgm:pt><dgm:pt modelId="{CF68E66B-81B1-4AB0-A4A3-37F3E6CF3FDD}" type="pres"><dgm:prSet presAssocID="{FB46E635-D183-4F54-8BA4-9110B2596327}" presName="background4" presStyleLbl="node4" presStyleIdx="3" presStyleCnt="4"/><dgm:spPr><a:solidFill><a:srgbClr val="9BBB59"/></a:solidFill></dgm:spPr></dgm:pt><dgm:pt modelId="{27F092DC-79E6-4FD2-B7AF-6D142CF267A2}" type="pres"><dgm:prSet presAssocID="{FB46E635-D183-4F54-8BA4-9110B2596327}" presName="text4" presStyleLbl="fgAcc4" presStyleIdx="3" presStyleCnt="4" custLinFactNeighborY="2296"><dgm:presLayoutVars><dgm:chPref val="3"/></dgm:presLayoutVars></dgm:prSet><dgm:spPr/></dgm:pt><dgm:pt modelId="{C29521F7-04AE-408D-9B55-BE0119E3E45C}" type="pres"><dgm:prSet presAssocID="{FB46E635-D183-4F54-8BA4-9110B2596327}" presName="hierChild5" presStyleCnt="0"/><dgm:spPr/></dgm:pt></dgm:ptLst><dgm:cxnLst><dgm:cxn modelId="{05611C05-D6E2-4E7D-A7F7-1060B863B584}" srcId="{05BDFADE-6B6F-4D19-98E0-6ACAEB9649B4}" destId="{DD98DB28-CA2B-4A19-99B3-1C1F6085434A}" srcOrd="0" destOrd="0" parTransId="{A6CBA7F9-CB2A-42C1-9FE4-9EAFFEC75D12}" sibTransId="{F31179F2-E126-4C3C-8442-C7BEC8BE37C2}"/><dgm:cxn modelId="{39ECDE05-2691-4F35-BDED-312F2E6BB735}" type="presOf" srcId="{B559931F-0554-4F1D-80F8-163E8A3E72B8}" destId="{F276219D-E0D2-49A4-86FC-71103CE17672}" srcOrd="0" destOrd="0" presId="urn:microsoft.com/office/officeart/2005/8/layout/hierarchy1"/><dgm:cxn modelId="{C9653809-6B59-4C54-92DC-A8884B116B17}" srcId="{DD98DB28-CA2B-4A19-99B3-1C1F6085434A}" destId="{67A9F40C-B22D-45C5-8B1B-AB3F98EBB3DE}" srcOrd="1" destOrd="0" parTransId="{A777C4DF-5FCC-4D66-8D77-B564D2682045}" sibTransId="{1263A584-A52B-4B65-83EF-0C9F5678DD02}"/><dgm:cxn modelId="{AED03D14-9C2E-4698-B498-A239DC4575CC}" srcId="{02F41359-2000-4693-B51C-D967970F9871}" destId="{68C4B14F-3DED-4A9C-A5AC-313677F26E4F}" srcOrd="0" destOrd="0" parTransId="{26AAA6C6-3DAE-4739-8959-6FC98F7D7238}" sibTransId="{7C98A040-E3CE-4BF2-9108-8E6D6AD58D18}"/><dgm:cxn modelId="{88CCDF1D-427D-426B-B72D-02A1F53C46C1}" type="presOf" srcId="{A96E9E58-1A5E-4BB9-AE14-E44A1CD64E45}" destId="{30E72103-622E-4ACB-BB4F-9A636E26B64D}" srcOrd="0" destOrd="0" presId="urn:microsoft.com/office/officeart/2005/8/layout/hierarchy1"/><dgm:cxn modelId="{374AE921-4180-4C72-BC36-A3B44D8803C8}" srcId="{05BDFADE-6B6F-4D19-98E0-6ACAEB9649B4}" destId="{02F41359-2000-4693-B51C-D967970F9871}" srcOrd="1" destOrd="0" parTransId="{193F5744-2EB9-42B6-9B29-5BD876DA8A15}" sibTransId="{FAA884DF-D7AB-45D7-A43A-AFEC95F3C97F}"/><dgm:cxn modelId="{3EF9E52A-2A6C-4EF2-8FBC-1A0775E6B690}" type="presOf" srcId="{68C4B14F-3DED-4A9C-A5AC-313677F26E4F}" destId="{A457F630-2A04-4DEA-8698-6A3F471ECBD7}" srcOrd="0" destOrd="0" presId="urn:microsoft.com/office/officeart/2005/8/layout/hierarchy1"/><dgm:cxn modelId="{299B5B44-73EF-472A-9A20-452E685B02D1}" srcId="{E76F06C7-BB5C-415B-BDAE-38A0DBDD95D9}" destId="{4B3C98DA-860F-4098-A26A-812D56B96FE3}" srcOrd="0" destOrd="0" parTransId="{D7A1B228-CBCA-4026-AAD5-F680D9FB6214}" sibTransId="{C037B149-D302-4A19-B00E-68317EEEC897}"/><dgm:cxn modelId="{ECF6546A-EE91-4290-BA49-8FC7AA4855B5}" type="presOf" srcId="{6C6D8593-343D-4604-8053-5ECF3A36871A}" destId="{EB4B47D3-78C9-4A29-8831-253E60AB2C95}" srcOrd="0" destOrd="0" presId="urn:microsoft.com/office/officeart/2005/8/layout/hierarchy1"/><dgm:cxn modelId="{6E968454-D40C-4638-9F0A-9B41FECA61DB}" type="presOf" srcId="{FB46E635-D183-4F54-8BA4-9110B2596327}" destId="{27F092DC-79E6-4FD2-B7AF-6D142CF267A2}" srcOrd="0" destOrd="0" presId="urn:microsoft.com/office/officeart/2005/8/layout/hierarchy1"/><dgm:cxn modelId="{A1DF8E58-95FC-4748-9BCB-306CD603B32A}" type="presOf" srcId="{4B3C98DA-860F-4098-A26A-812D56B96FE3}" destId="{CA59AF42-B5D3-474D-9E4F-45BF6E07B1B8}" srcOrd="0" destOrd="0" presId="urn:microsoft.com/office/officeart/2005/8/layout/hierarchy1"/><dgm:cxn modelId="{CA0A0E79-ED2A-402D-8E75-4A33CA3E3955}" type="presOf" srcId="{67A9F40C-B22D-45C5-8B1B-AB3F98EBB3DE}" destId="{A1347397-5D99-4DCE-9F90-3FCEF6D40048}" srcOrd="0" destOrd="0" presId="urn:microsoft.com/office/officeart/2005/8/layout/hierarchy1"/><dgm:cxn modelId="{342E0A7B-A429-4D09-968B-8F8B7BBF5E97}" type="presOf" srcId="{DD98DB28-CA2B-4A19-99B3-1C1F6085434A}" destId="{BEAD8990-338B-4972-9DC9-5297E63253C1}" srcOrd="0" destOrd="0" presId="urn:microsoft.com/office/officeart/2005/8/layout/hierarchy1"/><dgm:cxn modelId="{E7B76884-BEA4-48E5-8F1C-E7122EBBDDB2}" type="presOf" srcId="{A6CBA7F9-CB2A-42C1-9FE4-9EAFFEC75D12}" destId="{61C43B60-00B9-4137-93C9-E6549E07BA5C}" srcOrd="0" destOrd="0" presId="urn:microsoft.com/office/officeart/2005/8/layout/hierarchy1"/><dgm:cxn modelId="{398FB98F-DC57-4B5E-A149-4C5B2F2829E3}" srcId="{DD98DB28-CA2B-4A19-99B3-1C1F6085434A}" destId="{86E60FF7-EBD9-49C9-B604-08A63D05DEC8}" srcOrd="0" destOrd="0" parTransId="{B4386F82-6DBA-4CD9-BCDF-F17AAFB1216B}" sibTransId="{2E1F1054-5F65-4FF4-9C60-C33979D0E2A7}"/><dgm:cxn modelId="{69C79EA0-D5D2-41B8-B53B-CCA6393876B5}" srcId="{E76F06C7-BB5C-415B-BDAE-38A0DBDD95D9}" destId="{05BDFADE-6B6F-4D19-98E0-6ACAEB9649B4}" srcOrd="1" destOrd="0" parTransId="{6C6D8593-343D-4604-8053-5ECF3A36871A}" sibTransId="{DB30FD50-4436-4A47-A24F-7492AAE34863}"/><dgm:cxn modelId="{1C85A0B1-7B3C-4AC9-9DAE-1C3F92E03828}" type="presOf" srcId="{B4386F82-6DBA-4CD9-BCDF-F17AAFB1216B}" destId="{36A0FDEF-9C80-44BF-B9C9-963DE8FF2ABD}" srcOrd="0" destOrd="0" presId="urn:microsoft.com/office/officeart/2005/8/layout/hierarchy1"/><dgm:cxn modelId="{2425A7B1-AF58-49EB-85B3-C0877E9FE11D}" type="presOf" srcId="{86E60FF7-EBD9-49C9-B604-08A63D05DEC8}" destId="{BA344F40-DA45-4713-8AA1-6D47DB5F0C83}" srcOrd="0" destOrd="0" presId="urn:microsoft.com/office/officeart/2005/8/layout/hierarchy1"/><dgm:cxn modelId="{6B1E00B6-CC8A-48F7-B80A-FF59791FDE0A}" type="presOf" srcId="{26AAA6C6-3DAE-4739-8959-6FC98F7D7238}" destId="{59F2ED9D-EEDE-4E12-8072-0E20DE4B1984}" srcOrd="0" destOrd="0" presId="urn:microsoft.com/office/officeart/2005/8/layout/hierarchy1"/><dgm:cxn modelId="{CA6487C3-47F8-4154-A034-459EED42576B}" srcId="{A96E9E58-1A5E-4BB9-AE14-E44A1CD64E45}" destId="{E76F06C7-BB5C-415B-BDAE-38A0DBDD95D9}" srcOrd="0" destOrd="0" parTransId="{61981EB0-B651-4EAC-8E55-D76B8460F4D7}" sibTransId="{4AB4D94D-8F15-4480-8CAE-BE949D7A7DD2}"/><dgm:cxn modelId="{81C689C8-949F-4558-BE61-7FDBA8143A95}" srcId="{02F41359-2000-4693-B51C-D967970F9871}" destId="{FB46E635-D183-4F54-8BA4-9110B2596327}" srcOrd="1" destOrd="0" parTransId="{B559931F-0554-4F1D-80F8-163E8A3E72B8}" sibTransId="{D063BEA2-BFC1-4AEC-BDA1-F403A9141D03}"/><dgm:cxn modelId="{6DF8C5D6-3FC9-4D5D-B5B7-D85E02A3A58E}" type="presOf" srcId="{05BDFADE-6B6F-4D19-98E0-6ACAEB9649B4}" destId="{1187A332-BE58-497C-B62A-E67BD2F7CA03}" srcOrd="0" destOrd="0" presId="urn:microsoft.com/office/officeart/2005/8/layout/hierarchy1"/><dgm:cxn modelId="{CC9A40DE-F2C1-403D-8797-539DBC898145}" type="presOf" srcId="{A777C4DF-5FCC-4D66-8D77-B564D2682045}" destId="{FA728B40-8594-4EE3-AEF0-42F442E6CF53}" srcOrd="0" destOrd="0" presId="urn:microsoft.com/office/officeart/2005/8/layout/hierarchy1"/><dgm:cxn modelId="{B8D9CEEA-D548-4CE3-8781-B5ADF62827F2}" type="presOf" srcId="{D7A1B228-CBCA-4026-AAD5-F680D9FB6214}" destId="{ED9BEC03-655F-4B72-8B6D-866E2222F1B1}" srcOrd="0" destOrd="0" presId="urn:microsoft.com/office/officeart/2005/8/layout/hierarchy1"/><dgm:cxn modelId="{4AED4EEB-C3CC-4A19-981E-A83907C2270A}" type="presOf" srcId="{193F5744-2EB9-42B6-9B29-5BD876DA8A15}" destId="{14059B0E-1C24-430B-8153-F310BF4A40A3}" srcOrd="0" destOrd="0" presId="urn:microsoft.com/office/officeart/2005/8/layout/hierarchy1"/><dgm:cxn modelId="{2407C3F4-6C46-43AE-A669-A282373A1D76}" type="presOf" srcId="{02F41359-2000-4693-B51C-D967970F9871}" destId="{252360A4-7143-4832-B1D6-16B6DB19483C}" srcOrd="0" destOrd="0" presId="urn:microsoft.com/office/officeart/2005/8/layout/hierarchy1"/><dgm:cxn modelId="{8FFB97F6-5D9C-41FA-9D04-FDE7B70F6642}" type="presOf" srcId="{E76F06C7-BB5C-415B-BDAE-38A0DBDD95D9}" destId="{66EFAB48-B846-4945-A919-92AD5F3E65F0}" srcOrd="0" destOrd="0" presId="urn:microsoft.com/office/officeart/2005/8/layout/hierarchy1"/><dgm:cxn modelId="{B667BF54-6CB7-4102-8D1B-8599641AF0B7}" type="presParOf" srcId="{30E72103-622E-4ACB-BB4F-9A636E26B64D}" destId="{1646D6ED-3346-445B-8D04-73973487F8C7}" srcOrd="0" destOrd="0" presId="urn:microsoft.com/office/officeart/2005/8/layout/hierarchy1"/><dgm:cxn modelId="{B8AECD8F-1F0A-4348-8B73-6F09AA2441C0}" type="presParOf" srcId="{1646D6ED-3346-445B-8D04-73973487F8C7}" destId="{2A76C565-2D05-47DB-90BA-AD4D577F949A}" srcOrd="0" destOrd="0" presId="urn:microsoft.com/office/officeart/2005/8/layout/hierarchy1"/><dgm:cxn modelId="{3CD60F1F-B39F-488D-AAC1-E41042DA5F14}" type="presParOf" srcId="{2A76C565-2D05-47DB-90BA-AD4D577F949A}" destId="{98EA51C6-BB0E-4BBB-8987-F50B0E13E36C}" srcOrd="0" destOrd="0" presId="urn:microsoft.com/office/officeart/2005/8/layout/hierarchy1"/><dgm:cxn modelId="{E18BE2E0-9B9F-4A47-8C57-913AAAB6E516}" type="presParOf" srcId="{2A76C565-2D05-47DB-90BA-AD4D577F949A}" destId="{66EFAB48-B846-4945-A919-92AD5F3E65F0}" srcOrd="1" destOrd="0" presId="urn:microsoft.com/office/officeart/2005/8/layout/hierarchy1"/><dgm:cxn modelId="{3928BE55-EA9E-44AB-BAED-9F88D3B80AF4}" type="presParOf" srcId="{1646D6ED-3346-445B-8D04-73973487F8C7}" destId="{947BD69F-2735-4826-957D-D3A159246506}" srcOrd="1" destOrd="0" presId="urn:microsoft.com/office/officeart/2005/8/layout/hierarchy1"/><dgm:cxn modelId="{1AB111DF-1C94-452E-9255-F25BEB4C146C}" type="presParOf" srcId="{947BD69F-2735-4826-957D-D3A159246506}" destId="{ED9BEC03-655F-4B72-8B6D-866E2222F1B1}" srcOrd="0" destOrd="0" presId="urn:microsoft.com/office/officeart/2005/8/layout/hierarchy1"/><dgm:cxn modelId="{2A6B1D1F-A456-4A49-A0B8-D39E6571B3FA}" type="presParOf" srcId="{947BD69F-2735-4826-957D-D3A159246506}" destId="{288D2679-5CAC-4A07-A0E7-D635C4A2F766}" srcOrd="1" destOrd="0" presId="urn:microsoft.com/office/officeart/2005/8/layout/hierarchy1"/><dgm:cxn modelId="{754FCD75-DDE4-4A81-91D0-980211B37C21}" type="presParOf" srcId="{288D2679-5CAC-4A07-A0E7-D635C4A2F766}" destId="{8309DB3B-8F84-4843-BDFD-CD3EDA2EBA64}" srcOrd="0" destOrd="0" presId="urn:microsoft.com/office/officeart/2005/8/layout/hierarchy1"/><dgm:cxn modelId="{4BB72E5A-B58F-4756-9930-51C90B9D67D7}" type="presParOf" srcId="{8309DB3B-8F84-4843-BDFD-CD3EDA2EBA64}" destId="{7D8D35D9-1812-4729-A852-740D72BB4BDE}" srcOrd="0" destOrd="0" presId="urn:microsoft.com/office/officeart/2005/8/layout/hierarchy1"/><dgm:cxn modelId="{5ED73490-55D6-4DC5-852B-55692AC613CB}" type="presParOf" srcId="{8309DB3B-8F84-4843-BDFD-CD3EDA2EBA64}" destId="{CA59AF42-B5D3-474D-9E4F-45BF6E07B1B8}" srcOrd="1" destOrd="0" presId="urn:microsoft.com/office/officeart/2005/8/layout/hierarchy1"/><dgm:cxn modelId="{40210F58-F5FD-424A-A68C-BBD79F4B404A}" type="presParOf" srcId="{288D2679-5CAC-4A07-A0E7-D635C4A2F766}" destId="{E2296C62-622F-4DA1-AE18-38FF9E99676E}" srcOrd="1" destOrd="0" presId="urn:microsoft.com/office/officeart/2005/8/layout/hierarchy1"/><dgm:cxn modelId="{24C2F6FA-0893-4F88-8B37-B3F62661F9C6}" type="presParOf" srcId="{947BD69F-2735-4826-957D-D3A159246506}" destId="{EB4B47D3-78C9-4A29-8831-253E60AB2C95}" srcOrd="2" destOrd="0" presId="urn:microsoft.com/office/officeart/2005/8/layout/hierarchy1"/><dgm:cxn modelId="{F4C2071E-2E47-42FB-91EF-4E42C4DA5549}" type="presParOf" srcId="{947BD69F-2735-4826-957D-D3A159246506}" destId="{1D6866E3-A80C-473C-A05E-D946ADDB3DD8}" srcOrd="3" destOrd="0" presId="urn:microsoft.com/office/officeart/2005/8/layout/hierarchy1"/><dgm:cxn modelId="{B8806F98-4569-49D9-A52C-04F9F0536FF0}" type="presParOf" srcId="{1D6866E3-A80C-473C-A05E-D946ADDB3DD8}" destId="{145FAFC4-CB1D-4556-B216-957535E47B91}" srcOrd="0" destOrd="0" presId="urn:microsoft.com/office/officeart/2005/8/layout/hierarchy1"/><dgm:cxn modelId="{03DF9CB9-7F50-4753-91D1-24F31EFF8DD5}" type="presParOf" srcId="{145FAFC4-CB1D-4556-B216-957535E47B91}" destId="{05C36326-416D-49BE-9197-E5D8C34C6C47}" srcOrd="0" destOrd="0" presId="urn:microsoft.com/office/officeart/2005/8/layout/hierarchy1"/><dgm:cxn modelId="{E1280F2F-B3A1-4697-A415-EA9FEDB90EA0}" type="presParOf" srcId="{145FAFC4-CB1D-4556-B216-957535E47B91}" destId="{1187A332-BE58-497C-B62A-E67BD2F7CA03}" srcOrd="1" destOrd="0" presId="urn:microsoft.com/office/officeart/2005/8/layout/hierarchy1"/><dgm:cxn modelId="{57D8B47F-01CD-4208-BBC0-6156606585E2}" type="presParOf" srcId="{1D6866E3-A80C-473C-A05E-D946ADDB3DD8}" destId="{918E4B51-D1C3-438F-BC8A-983398D37926}" srcOrd="1" destOrd="0" presId="urn:microsoft.com/office/officeart/2005/8/layout/hierarchy1"/><dgm:cxn modelId="{F8C0306E-F9C9-4DF6-909C-FB85798674A9}" type="presParOf" srcId="{918E4B51-D1C3-438F-BC8A-983398D37926}" destId="{61C43B60-00B9-4137-93C9-E6549E07BA5C}" srcOrd="0" destOrd="0" presId="urn:microsoft.com/office/officeart/2005/8/layout/hierarchy1"/><dgm:cxn modelId="{A4AC8547-F171-4706-B6FD-2DB285CDC195}" type="presParOf" srcId="{918E4B51-D1C3-438F-BC8A-983398D37926}" destId="{C40041AA-B6AD-4498-B8E6-7B97E19E427B}" srcOrd="1" destOrd="0" presId="urn:microsoft.com/office/officeart/2005/8/layout/hierarchy1"/><dgm:cxn modelId="{D5672171-A6E8-46B7-AF13-7B8754A42636}" type="presParOf" srcId="{C40041AA-B6AD-4498-B8E6-7B97E19E427B}" destId="{69B18AE8-1D52-4824-95F7-9D0BFC9E926F}" srcOrd="0" destOrd="0" presId="urn:microsoft.com/office/officeart/2005/8/layout/hierarchy1"/><dgm:cxn modelId="{4298E853-683C-4BA5-907B-554D5A8510E2}" type="presParOf" srcId="{69B18AE8-1D52-4824-95F7-9D0BFC9E926F}" destId="{FC7B7AB0-041A-4648-AF06-E2BFCE5DC72E}" srcOrd="0" destOrd="0" presId="urn:microsoft.com/office/officeart/2005/8/layout/hierarchy1"/><dgm:cxn modelId="{670D25BE-125A-4FB7-9E06-362CD324942F}" type="presParOf" srcId="{69B18AE8-1D52-4824-95F7-9D0BFC9E926F}" destId="{BEAD8990-338B-4972-9DC9-5297E63253C1}" srcOrd="1" destOrd="0" presId="urn:microsoft.com/office/officeart/2005/8/layout/hierarchy1"/><dgm:cxn modelId="{9FA60A6D-4C2B-45DC-B86F-69ECA6CCE64F}" type="presParOf" srcId="{C40041AA-B6AD-4498-B8E6-7B97E19E427B}" destId="{1170EE48-69DA-4684-BAFE-1636523EEF8B}" srcOrd="1" destOrd="0" presId="urn:microsoft.com/office/officeart/2005/8/layout/hierarchy1"/><dgm:cxn modelId="{FA7C7647-2A2F-4234-8BA0-EE4B2E5DA7B1}" type="presParOf" srcId="{1170EE48-69DA-4684-BAFE-1636523EEF8B}" destId="{36A0FDEF-9C80-44BF-B9C9-963DE8FF2ABD}" srcOrd="0" destOrd="0" presId="urn:microsoft.com/office/officeart/2005/8/layout/hierarchy1"/><dgm:cxn modelId="{C78B7865-DB9A-40EE-BAFD-96FA49C3DF41}" type="presParOf" srcId="{1170EE48-69DA-4684-BAFE-1636523EEF8B}" destId="{49ACFE62-E98F-4F23-8522-9519C1EDFC9C}" srcOrd="1" destOrd="0" presId="urn:microsoft.com/office/officeart/2005/8/layout/hierarchy1"/><dgm:cxn modelId="{8CFDCF0C-8213-4567-BF6B-972B51B65CA3}" type="presParOf" srcId="{49ACFE62-E98F-4F23-8522-9519C1EDFC9C}" destId="{FBB4F7F3-FDFD-4C7A-B357-BE66D7324673}" srcOrd="0" destOrd="0" presId="urn:microsoft.com/office/officeart/2005/8/layout/hierarchy1"/><dgm:cxn modelId="{4ED53047-2FDD-4A84-85A8-364AC728E97B}" type="presParOf" srcId="{FBB4F7F3-FDFD-4C7A-B357-BE66D7324673}" destId="{99E54DB5-A07A-4C23-9E88-AD6FFFC64D29}" srcOrd="0" destOrd="0" presId="urn:microsoft.com/office/officeart/2005/8/layout/hierarchy1"/><dgm:cxn modelId="{DC69E872-2511-46A5-9DD6-E72195E648BB}" type="presParOf" srcId="{FBB4F7F3-FDFD-4C7A-B357-BE66D7324673}" destId="{BA344F40-DA45-4713-8AA1-6D47DB5F0C83}" srcOrd="1" destOrd="0" presId="urn:microsoft.com/office/officeart/2005/8/layout/hierarchy1"/><dgm:cxn modelId="{FBC9F6A7-1AC7-4A11-AAE1-E68833F61BE9}" type="presParOf" srcId="{49ACFE62-E98F-4F23-8522-9519C1EDFC9C}" destId="{C91886EF-1172-4FF2-B434-958FAC969DF1}" srcOrd="1" destOrd="0" presId="urn:microsoft.com/office/officeart/2005/8/layout/hierarchy1"/><dgm:cxn modelId="{4D7B8D2F-101D-4740-8B43-A4253D32EE83}" type="presParOf" srcId="{1170EE48-69DA-4684-BAFE-1636523EEF8B}" destId="{FA728B40-8594-4EE3-AEF0-42F442E6CF53}" srcOrd="2" destOrd="0" presId="urn:microsoft.com/office/officeart/2005/8/layout/hierarchy1"/><dgm:cxn modelId="{D016092F-24B8-4208-B812-C569898A50A5}" type="presParOf" srcId="{1170EE48-69DA-4684-BAFE-1636523EEF8B}" destId="{A75D6FC5-BBA8-431C-B840-91B6FFAFA1C9}" srcOrd="3" destOrd="0" presId="urn:microsoft.com/office/officeart/2005/8/layout/hierarchy1"/><dgm:cxn modelId="{F0149321-FD28-4FF3-BB00-6A9888DBD5D3}" type="presParOf" srcId="{A75D6FC5-BBA8-431C-B840-91B6FFAFA1C9}" destId="{F4478BCD-E641-4D5E-873B-FEB04C50F7DB}" srcOrd="0" destOrd="0" presId="urn:microsoft.com/office/officeart/2005/8/layout/hierarchy1"/><dgm:cxn modelId="{99133AE8-1EBF-442C-983B-E68323C334FD}" type="presParOf" srcId="{F4478BCD-E641-4D5E-873B-FEB04C50F7DB}" destId="{D6A8E232-1D6E-41B1-AA98-A69997EDBE47}" srcOrd="0" destOrd="0" presId="urn:microsoft.com/office/officeart/2005/8/layout/hierarchy1"/><dgm:cxn modelId="{AB2D09F3-3909-4645-B48F-9A3B27F96052}" type="presParOf" srcId="{F4478BCD-E641-4D5E-873B-FEB04C50F7DB}" destId="{A1347397-5D99-4DCE-9F90-3FCEF6D40048}" srcOrd="1" destOrd="0" presId="urn:microsoft.com/office/officeart/2005/8/layout/hierarchy1"/><dgm:cxn modelId="{0116F11F-E81F-4133-8AAC-FA9895093DF7}" type="presParOf" srcId="{A75D6FC5-BBA8-431C-B840-91B6FFAFA1C9}" destId="{33A4A662-AE4A-463B-9B1C-E950C1FE1E0F}" srcOrd="1" destOrd="0" presId="urn:microsoft.com/office/officeart/2005/8/layout/hierarchy1"/><dgm:cxn modelId="{C1C335E8-2A82-4AF5-9037-85D140D3BF95}" type="presParOf" srcId="{918E4B51-D1C3-438F-BC8A-983398D37926}" destId="{14059B0E-1C24-430B-8153-F310BF4A40A3}" srcOrd="2" destOrd="0" presId="urn:microsoft.com/office/officeart/2005/8/layout/hierarchy1"/><dgm:cxn modelId="{D7D38805-71EB-478C-8231-D6561BB8D973}" type="presParOf" srcId="{918E4B51-D1C3-438F-BC8A-983398D37926}" destId="{31763496-D517-4508-9333-8D4DF4BFD4E0}" srcOrd="3" destOrd="0" presId="urn:microsoft.com/office/officeart/2005/8/layout/hierarchy1"/><dgm:cxn modelId="{F3DA46AD-B96E-4EC0-830B-00B9424C54AE}" type="presParOf" srcId="{31763496-D517-4508-9333-8D4DF4BFD4E0}" destId="{EEFA94E9-BF9D-44E2-A4CF-6E698545178C}" srcOrd="0" destOrd="0" presId="urn:microsoft.com/office/officeart/2005/8/layout/hierarchy1"/><dgm:cxn modelId="{185F988E-419A-4465-89A6-11D91FF37A60}" type="presParOf" srcId="{EEFA94E9-BF9D-44E2-A4CF-6E698545178C}" destId="{1639B34E-E530-43D4-92B0-CBB06896CDCD}" srcOrd="0" destOrd="0" presId="urn:microsoft.com/office/officeart/2005/8/layout/hierarchy1"/><dgm:cxn modelId="{7D6B17B3-60EC-4199-9DCC-C79A74BDED9C}" type="presParOf" srcId="{EEFA94E9-BF9D-44E2-A4CF-6E698545178C}" destId="{252360A4-7143-4832-B1D6-16B6DB19483C}" srcOrd="1" destOrd="0" presId="urn:microsoft.com/office/officeart/2005/8/layout/hierarchy1"/><dgm:cxn modelId="{65372FEA-238E-4AD1-A39A-713E63A22D6D}" type="presParOf" srcId="{31763496-D517-4508-9333-8D4DF4BFD4E0}" destId="{CE05A8D0-8B70-406D-93DF-17554536A2C0}" srcOrd="1" destOrd="0" presId="urn:microsoft.com/office/officeart/2005/8/layout/hierarchy1"/><dgm:cxn modelId="{40B94353-68E0-400A-B9BE-FA3C6E8667D5}" type="presParOf" srcId="{CE05A8D0-8B70-406D-93DF-17554536A2C0}" destId="{59F2ED9D-EEDE-4E12-8072-0E20DE4B1984}" srcOrd="0" destOrd="0" presId="urn:microsoft.com/office/officeart/2005/8/layout/hierarchy1"/><dgm:cxn modelId="{B9F5E1CA-20C9-4A4E-A7A6-A83072EBEF01}" type="presParOf" srcId="{CE05A8D0-8B70-406D-93DF-17554536A2C0}" destId="{9EF8BDCF-0B01-4690-8A60-A63831CC83EB}" srcOrd="1" destOrd="0" presId="urn:microsoft.com/office/officeart/2005/8/layout/hierarchy1"/><dgm:cxn modelId="{FEC4C64E-463A-47DC-896F-290E7C48F7CB}" type="presParOf" srcId="{9EF8BDCF-0B01-4690-8A60-A63831CC83EB}" destId="{8ED8A936-42DB-46F9-9751-D64C2969B269}" srcOrd="0" destOrd="0" presId="urn:microsoft.com/office/officeart/2005/8/layout/hierarchy1"/><dgm:cxn modelId="{15B1B872-547C-43F6-BA5C-CA168D930749}" type="presParOf" srcId="{8ED8A936-42DB-46F9-9751-D64C2969B269}" destId="{80A8E217-4055-4BD3-9111-BD3FD28D2F74}" srcOrd="0" destOrd="0" presId="urn:microsoft.com/office/officeart/2005/8/layout/hierarchy1"/><dgm:cxn modelId="{55FE75FD-163C-46A6-8496-4B257E51609C}" type="presParOf" srcId="{8ED8A936-42DB-46F9-9751-D64C2969B269}" destId="{A457F630-2A04-4DEA-8698-6A3F471ECBD7}" srcOrd="1" destOrd="0" presId="urn:microsoft.com/office/officeart/2005/8/layout/hierarchy1"/><dgm:cxn modelId="{123D1561-350B-4235-92B3-6318FBF55400}" type="presParOf" srcId="{9EF8BDCF-0B01-4690-8A60-A63831CC83EB}" destId="{C913EE18-0A66-4209-95A5-804DCA3FDED9}" srcOrd="1" destOrd="0" presId="urn:microsoft.com/office/officeart/2005/8/layout/hierarchy1"/><dgm:cxn modelId="{F016861E-15C9-46B0-8ECC-39FABA985B27}" type="presParOf" srcId="{CE05A8D0-8B70-406D-93DF-17554536A2C0}" destId="{F276219D-E0D2-49A4-86FC-71103CE17672}" srcOrd="2" destOrd="0" presId="urn:microsoft.com/office/officeart/2005/8/layout/hierarchy1"/><dgm:cxn modelId="{28276C15-28F0-418E-9654-48282D2C47E9}" type="presParOf" srcId="{CE05A8D0-8B70-406D-93DF-17554536A2C0}" destId="{E8A540F5-EC80-4CD5-94E6-BCA1AA33D54A}" srcOrd="3" destOrd="0" presId="urn:microsoft.com/office/officeart/2005/8/layout/hierarchy1"/><dgm:cxn modelId="{3FA8BEAF-A1D3-4CDE-93FC-E4904ADE6BC8}" type="presParOf" srcId="{E8A540F5-EC80-4CD5-94E6-BCA1AA33D54A}" destId="{289ADCB4-A6A6-43BB-B38D-1DFC6E25B831}" srcOrd="0" destOrd="0" presId="urn:microsoft.com/office/officeart/2005/8/layout/hierarchy1"/><dgm:cxn modelId="{5B6F53CB-A00A-4DA8-A61F-BBC0BED217DF}" type="presParOf" srcId="{289ADCB4-A6A6-43BB-B38D-1DFC6E25B831}" destId="{CF68E66B-81B1-4AB0-A4A3-37F3E6CF3FDD}" srcOrd="0" destOrd="0" presId="urn:microsoft.com/office/officeart/2005/8/layout/hierarchy1"/><dgm:cxn modelId="{80EB568C-25DD-4A3C-ACEF-51BD7624D220}" type="presParOf" srcId="{289ADCB4-A6A6-43BB-B38D-1DFC6E25B831}" destId="{27F092DC-79E6-4FD2-B7AF-6D142CF267A2}" srcOrd="1" destOrd="0" presId="urn:microsoft.com/office/officeart/2005/8/layout/hierarchy1"/><dgm:cxn modelId="{C15B39CB-3AF3-4E58-8CF4-90E5D3709F2F}" type="presParOf" srcId="{E8A540F5-EC80-4CD5-94E6-BCA1AA33D54A}" destId="{C29521F7-04AE-408D-9B55-BE0119E3E45C}" srcOrd="1" destOrd="0" presId="urn:microsoft.com/office/officeart/2005/8/layout/hierarchy1"/></dgm:cxnLst><dgm:bg/><dgm:whole/><dgm:extLst><a:ext uri="http://schemas.microsoft.com/office/drawing/2008/diagram"><dsp:dataModelExt xmlns:dsp="http://schemas.microsoft.com/office/drawing/2008/diagram" relId="rId222" minVer="http://schemas.openxmlformats.org/drawingml/2006/diagram"/></a:ext></dgm:extLst></dgm:dataModel>