<?xml version="1.0" encoding="UTF-8" standalone="yes"?>
<dgm:dataModel xmlns:dgm="http://schemas.openxmlformats.org/drawingml/2006/diagram" xmlns:a="http://schemas.openxmlformats.org/drawingml/2006/main"><dgm:ptLst><dgm:pt modelId="{CE857CBF-37A9-41C2-B8E5-9223CDB45BCB}" type="doc"><dgm:prSet loTypeId="urn:microsoft.com/office/officeart/2005/8/layout/equation2" loCatId="relationship" qsTypeId="urn:microsoft.com/office/officeart/2005/8/quickstyle/simple1" qsCatId="simple" csTypeId="urn:microsoft.com/office/officeart/2005/8/colors/accent1_2" csCatId="accent1" phldr="1"/><dgm:spPr/></dgm:pt><dgm:pt modelId="{B376F3FD-2550-49F9-A4C9-2A5ADE47C62B}"><dgm:prSet phldrT="[Text]"/><dgm:spPr><a:solidFill><a:schemeClr val="accent2"><a:lumMod val="75000"/></a:schemeClr></a:solidFill></dgm:spPr><dgm:t><a:bodyPr/><a:lstStyle/><a:p><a:r><a:rPr lang="sv-SE"/><a:t>Bengta Jönsdotter</a:t></a:r></a:p><a:p><a:r><a:rPr lang="sv-SE"/><a:t>1838-1901</a:t></a:r></a:p></dgm:t></dgm:pt><dgm:pt modelId="{50DE726A-CCE1-44B1-BAF2-4790187EF878}" type="parTrans" cxnId="{34D7001C-5F84-4E18-9572-1E829815D83E}"><dgm:prSet/><dgm:spPr/><dgm:t><a:bodyPr/><a:lstStyle/><a:p><a:endParaRPr lang="sv-SE"/></a:p></dgm:t></dgm:pt><dgm:pt modelId="{8F54CE6E-EF6E-4AD4-A9D4-02FB370DA3FF}" type="sibTrans" cxnId="{34D7001C-5F84-4E18-9572-1E829815D83E}"><dgm:prSet/><dgm:spPr/><dgm:t><a:bodyPr/><a:lstStyle/><a:p><a:endParaRPr lang="sv-SE"/></a:p></dgm:t></dgm:pt><dgm:pt modelId="{9B944063-1395-416E-B380-57D93628C62B}"><dgm:prSet phldrT="[Text]"/><dgm:spPr><a:solidFill><a:schemeClr val="accent2"><a:lumMod val="75000"/></a:schemeClr></a:solidFill></dgm:spPr><dgm:t><a:bodyPr/><a:lstStyle/><a:p><a:r><a:rPr lang="sv-SE"/><a:t>Nils Andersson</a:t></a:r></a:p><a:p><a:r><a:rPr lang="sv-SE"/><a:t>1831-1898</a:t></a:r></a:p></dgm:t></dgm:pt><dgm:pt modelId="{0A488B63-0584-4069-A18F-ACA32E3B47B4}" type="parTrans" cxnId="{5B2BCBD5-FE0B-4C5A-965A-F622DF59FFD7}"><dgm:prSet/><dgm:spPr/><dgm:t><a:bodyPr/><a:lstStyle/><a:p><a:endParaRPr lang="sv-SE"/></a:p></dgm:t></dgm:pt><dgm:pt modelId="{9A1375C0-A11C-4514-8F30-5638DD27F480}" type="sibTrans" cxnId="{5B2BCBD5-FE0B-4C5A-965A-F622DF59FFD7}"><dgm:prSet/><dgm:spPr/><dgm:t><a:bodyPr/><a:lstStyle/><a:p><a:endParaRPr lang="sv-SE"/></a:p></dgm:t></dgm:pt><dgm:pt modelId="{9DC68451-471A-4658-9E46-90700277A951}"><dgm:prSet phldrT="[Text]"/><dgm:spPr><a:solidFill><a:schemeClr val="accent1"><a:lumMod val="75000"/></a:schemeClr></a:solidFill></dgm:spPr><dgm:t><a:bodyPr/><a:lstStyle/><a:p><a:r><a:rPr lang="sv-SE"/><a:t>Anna Andersson</a:t></a:r></a:p><a:p><a:r><a:rPr lang="sv-SE"/><a:t>1879-1947</a:t></a:r></a:p></dgm:t></dgm:pt><dgm:pt modelId="{8F835BAF-083C-4990-BC5C-00391D91D6BC}" type="parTrans" cxnId="{B7003900-EE72-4988-AFDA-CF13B591F077}"><dgm:prSet/><dgm:spPr/><dgm:t><a:bodyPr/><a:lstStyle/><a:p><a:endParaRPr lang="sv-SE"/></a:p></dgm:t></dgm:pt><dgm:pt modelId="{C5329627-F8E1-4666-8B0E-83155C9602DF}" type="sibTrans" cxnId="{B7003900-EE72-4988-AFDA-CF13B591F077}"><dgm:prSet/><dgm:spPr/><dgm:t><a:bodyPr/><a:lstStyle/><a:p><a:endParaRPr lang="sv-SE"/></a:p></dgm:t></dgm:pt><dgm:pt modelId="{0A61523C-5129-4A4D-B58D-8A172FAD28D8}" type="pres"><dgm:prSet presAssocID="{CE857CBF-37A9-41C2-B8E5-9223CDB45BCB}" presName="Name0" presStyleCnt="0"><dgm:presLayoutVars><dgm:dir/><dgm:resizeHandles val="exact"/></dgm:presLayoutVars></dgm:prSet><dgm:spPr/></dgm:pt><dgm:pt modelId="{0B4F23A6-C7CC-4E32-B4ED-EEBA12B00733}" type="pres"><dgm:prSet presAssocID="{CE857CBF-37A9-41C2-B8E5-9223CDB45BCB}" presName="vNodes" presStyleCnt="0"/><dgm:spPr/></dgm:pt><dgm:pt modelId="{8B29B7D0-E4EE-4038-A253-2801BF170D39}" type="pres"><dgm:prSet presAssocID="{B376F3FD-2550-49F9-A4C9-2A5ADE47C62B}" presName="node" presStyleLbl="node1" presStyleIdx="0" presStyleCnt="3"><dgm:presLayoutVars><dgm:bulletEnabled val="1"/></dgm:presLayoutVars></dgm:prSet><dgm:spPr/></dgm:pt><dgm:pt modelId="{A4A264C8-5AD0-4896-9977-1E8F58DAE31E}" type="pres"><dgm:prSet presAssocID="{8F54CE6E-EF6E-4AD4-A9D4-02FB370DA3FF}" presName="spacerT" presStyleCnt="0"/><dgm:spPr/></dgm:pt><dgm:pt modelId="{DB77812C-D7EB-48A0-B13F-9996554BBF25}" type="pres"><dgm:prSet presAssocID="{8F54CE6E-EF6E-4AD4-A9D4-02FB370DA3FF}" presName="sibTrans" presStyleLbl="sibTrans2D1" presStyleIdx="0" presStyleCnt="2"/><dgm:spPr/></dgm:pt><dgm:pt modelId="{63957DB6-CD44-49C5-B34C-A3CAFCE61D6B}" type="pres"><dgm:prSet presAssocID="{8F54CE6E-EF6E-4AD4-A9D4-02FB370DA3FF}" presName="spacerB" presStyleCnt="0"/><dgm:spPr/></dgm:pt><dgm:pt modelId="{8D79A811-B8E2-4A31-B7AC-6A4905E9C36B}" type="pres"><dgm:prSet presAssocID="{9B944063-1395-416E-B380-57D93628C62B}" presName="node" presStyleLbl="node1" presStyleIdx="1" presStyleCnt="3"><dgm:presLayoutVars><dgm:bulletEnabled val="1"/></dgm:presLayoutVars></dgm:prSet><dgm:spPr/></dgm:pt><dgm:pt modelId="{2D49515D-3A40-4C16-AA86-7DF640231EBF}" type="pres"><dgm:prSet presAssocID="{CE857CBF-37A9-41C2-B8E5-9223CDB45BCB}" presName="sibTransLast" presStyleLbl="sibTrans2D1" presStyleIdx="1" presStyleCnt="2"/><dgm:spPr/></dgm:pt><dgm:pt modelId="{F8A94F5A-8B28-40D9-928B-B1D5341084A9}" type="pres"><dgm:prSet presAssocID="{CE857CBF-37A9-41C2-B8E5-9223CDB45BCB}" presName="connectorText" presStyleLbl="sibTrans2D1" presStyleIdx="1" presStyleCnt="2"/><dgm:spPr/></dgm:pt><dgm:pt modelId="{B8AB6CBC-6193-4C1C-9761-7758BDA880F7}" type="pres"><dgm:prSet presAssocID="{CE857CBF-37A9-41C2-B8E5-9223CDB45BCB}" presName="lastNode" presStyleLbl="node1" presStyleIdx="2" presStyleCnt="3"><dgm:presLayoutVars><dgm:bulletEnabled val="1"/></dgm:presLayoutVars></dgm:prSet><dgm:spPr/></dgm:pt></dgm:ptLst><dgm:cxnLst><dgm:cxn modelId="{B7003900-EE72-4988-AFDA-CF13B591F077}" srcId="{CE857CBF-37A9-41C2-B8E5-9223CDB45BCB}" destId="{9DC68451-471A-4658-9E46-90700277A951}" srcOrd="2" destOrd="0" parTransId="{8F835BAF-083C-4990-BC5C-00391D91D6BC}" sibTransId="{C5329627-F8E1-4666-8B0E-83155C9602DF}"/><dgm:cxn modelId="{973B6B08-533A-4925-A1EC-4F96950790B1}" type="presOf" srcId="{9A1375C0-A11C-4514-8F30-5638DD27F480}" destId="{F8A94F5A-8B28-40D9-928B-B1D5341084A9}" srcOrd="1" destOrd="0" presId="urn:microsoft.com/office/officeart/2005/8/layout/equation2"/><dgm:cxn modelId="{34D7001C-5F84-4E18-9572-1E829815D83E}" srcId="{CE857CBF-37A9-41C2-B8E5-9223CDB45BCB}" destId="{B376F3FD-2550-49F9-A4C9-2A5ADE47C62B}" srcOrd="0" destOrd="0" parTransId="{50DE726A-CCE1-44B1-BAF2-4790187EF878}" sibTransId="{8F54CE6E-EF6E-4AD4-A9D4-02FB370DA3FF}"/><dgm:cxn modelId="{82C95936-2AC4-4DE1-8851-D37C25CCA04B}" type="presOf" srcId="{8F54CE6E-EF6E-4AD4-A9D4-02FB370DA3FF}" destId="{DB77812C-D7EB-48A0-B13F-9996554BBF25}" srcOrd="0" destOrd="0" presId="urn:microsoft.com/office/officeart/2005/8/layout/equation2"/><dgm:cxn modelId="{FCBCECA4-A96B-415C-BE1C-9CC8316C72D1}" type="presOf" srcId="{B376F3FD-2550-49F9-A4C9-2A5ADE47C62B}" destId="{8B29B7D0-E4EE-4038-A253-2801BF170D39}" srcOrd="0" destOrd="0" presId="urn:microsoft.com/office/officeart/2005/8/layout/equation2"/><dgm:cxn modelId="{538417C4-88A1-4D2E-9436-4FC29ED97879}" type="presOf" srcId="{9DC68451-471A-4658-9E46-90700277A951}" destId="{B8AB6CBC-6193-4C1C-9761-7758BDA880F7}" srcOrd="0" destOrd="0" presId="urn:microsoft.com/office/officeart/2005/8/layout/equation2"/><dgm:cxn modelId="{364C67C6-FB4F-4021-A5A4-EC002FE32333}" type="presOf" srcId="{9A1375C0-A11C-4514-8F30-5638DD27F480}" destId="{2D49515D-3A40-4C16-AA86-7DF640231EBF}" srcOrd="0" destOrd="0" presId="urn:microsoft.com/office/officeart/2005/8/layout/equation2"/><dgm:cxn modelId="{96C006D2-E44E-4A3D-AC7F-B80AB4F1D433}" type="presOf" srcId="{CE857CBF-37A9-41C2-B8E5-9223CDB45BCB}" destId="{0A61523C-5129-4A4D-B58D-8A172FAD28D8}" srcOrd="0" destOrd="0" presId="urn:microsoft.com/office/officeart/2005/8/layout/equation2"/><dgm:cxn modelId="{5B2BCBD5-FE0B-4C5A-965A-F622DF59FFD7}" srcId="{CE857CBF-37A9-41C2-B8E5-9223CDB45BCB}" destId="{9B944063-1395-416E-B380-57D93628C62B}" srcOrd="1" destOrd="0" parTransId="{0A488B63-0584-4069-A18F-ACA32E3B47B4}" sibTransId="{9A1375C0-A11C-4514-8F30-5638DD27F480}"/><dgm:cxn modelId="{C110E5E5-DC08-426E-BD54-A7135E403F95}" type="presOf" srcId="{9B944063-1395-416E-B380-57D93628C62B}" destId="{8D79A811-B8E2-4A31-B7AC-6A4905E9C36B}" srcOrd="0" destOrd="0" presId="urn:microsoft.com/office/officeart/2005/8/layout/equation2"/><dgm:cxn modelId="{A44D176F-3F25-487D-9DEF-CFC246BFB6EA}" type="presParOf" srcId="{0A61523C-5129-4A4D-B58D-8A172FAD28D8}" destId="{0B4F23A6-C7CC-4E32-B4ED-EEBA12B00733}" srcOrd="0" destOrd="0" presId="urn:microsoft.com/office/officeart/2005/8/layout/equation2"/><dgm:cxn modelId="{A176D03A-CAF4-4795-9BEB-AB1E6781D1E4}" type="presParOf" srcId="{0B4F23A6-C7CC-4E32-B4ED-EEBA12B00733}" destId="{8B29B7D0-E4EE-4038-A253-2801BF170D39}" srcOrd="0" destOrd="0" presId="urn:microsoft.com/office/officeart/2005/8/layout/equation2"/><dgm:cxn modelId="{AC5CAB1E-63F2-4E02-B01D-5C3776A62319}" type="presParOf" srcId="{0B4F23A6-C7CC-4E32-B4ED-EEBA12B00733}" destId="{A4A264C8-5AD0-4896-9977-1E8F58DAE31E}" srcOrd="1" destOrd="0" presId="urn:microsoft.com/office/officeart/2005/8/layout/equation2"/><dgm:cxn modelId="{A99CA2DD-9152-4B57-84BC-55313554947A}" type="presParOf" srcId="{0B4F23A6-C7CC-4E32-B4ED-EEBA12B00733}" destId="{DB77812C-D7EB-48A0-B13F-9996554BBF25}" srcOrd="2" destOrd="0" presId="urn:microsoft.com/office/officeart/2005/8/layout/equation2"/><dgm:cxn modelId="{D2362FC7-A397-469A-A626-FDEECFA6E931}" type="presParOf" srcId="{0B4F23A6-C7CC-4E32-B4ED-EEBA12B00733}" destId="{63957DB6-CD44-49C5-B34C-A3CAFCE61D6B}" srcOrd="3" destOrd="0" presId="urn:microsoft.com/office/officeart/2005/8/layout/equation2"/><dgm:cxn modelId="{A9FF74D6-1902-40F3-A1CD-75A522261D3B}" type="presParOf" srcId="{0B4F23A6-C7CC-4E32-B4ED-EEBA12B00733}" destId="{8D79A811-B8E2-4A31-B7AC-6A4905E9C36B}" srcOrd="4" destOrd="0" presId="urn:microsoft.com/office/officeart/2005/8/layout/equation2"/><dgm:cxn modelId="{5A738C1E-6F90-4DC9-98AB-7918ED404D7A}" type="presParOf" srcId="{0A61523C-5129-4A4D-B58D-8A172FAD28D8}" destId="{2D49515D-3A40-4C16-AA86-7DF640231EBF}" srcOrd="1" destOrd="0" presId="urn:microsoft.com/office/officeart/2005/8/layout/equation2"/><dgm:cxn modelId="{930F647F-86CC-4450-86AB-B004C8D11D10}" type="presParOf" srcId="{2D49515D-3A40-4C16-AA86-7DF640231EBF}" destId="{F8A94F5A-8B28-40D9-928B-B1D5341084A9}" srcOrd="0" destOrd="0" presId="urn:microsoft.com/office/officeart/2005/8/layout/equation2"/><dgm:cxn modelId="{5268FFAA-DA81-4318-931B-B2318CE31F60}" type="presParOf" srcId="{0A61523C-5129-4A4D-B58D-8A172FAD28D8}" destId="{B8AB6CBC-6193-4C1C-9761-7758BDA880F7}" srcOrd="2" destOrd="0" presId="urn:microsoft.com/office/officeart/2005/8/layout/equation2"/></dgm:cxnLst><dgm:bg/><dgm:whole/><dgm:extLst><a:ext uri="http://schemas.microsoft.com/office/drawing/2008/diagram"><dsp:dataModelExt xmlns:dsp="http://schemas.microsoft.com/office/drawing/2008/diagram" relId="rId161" minVer="http://schemas.openxmlformats.org/drawingml/2006/diagram"/></a:ext></dgm:extLst></dgm:dataModel>